{"$imgdir":"910041300.img","$$":[
  {"$imgdir":"info","$$":[
    {"$int":"version","value":"10"},
    {"$int":"cloud","value":"0"},
    {"$int":"town","value":"0"},
    {"$int":"swim","value":"0"},
    {"$int":"returnMap","value":"910040001"},
    {"$int":"forcedReturn","value":"910040001"},
    {"$float":"mobRate","value":"1.0"},
    {"$string":"bgm","value":"Bgm18/WolfAndSheep"},
    {"$string":"mapMark","value":"Event"},
    {"$int":"fly","value":"0"},
    {"$int":"noMapCmd","value":"0"},
    {"$int":"hideMinimap","value":"0"},
    {"$int":"fieldLimit","value":"337660"},
    {"$string":"onFirstUserEnter","value":""},
    {"$string":"onUserEnter","value":""},
    {"$int":"fieldType","value":"19"},
    {"$int":"VRTop","value":"-1230"},
    {"$int":"VRLeft","value":"-810"},
    {"$int":"VRBottom","value":"302"},
    {"$int":"VRRight","value":"1080"},
    {"$imgdir":"allowedItem","$$":[
      {"$int":"0","value":"2022539"},
      {"$int":"1","value":"2022540"},
      {"$int":"2","value":"2022541"},
      {"$int":"3","value":"2022542"},
      {"$int":"4","value":"2022543"},
      {"$int":"5","value":"2109004"},
      {"$int":"6","value":"2109005"},
      {"$int":"7","value":"2022547"},
      {"$int":"8","value":"2022548"},
      {"$int":"9","value":"2022549"}
    ]},
    {"$int":"dropExpire","value":"10"},
    {"$string":"link","value":"910040100"}
  ]}
]}