{"$imgdir":"910033300.img","$$":[
  {"$imgdir":"info","$$":[
    {"$int":"version","value":"10"},
    {"$int":"cloud","value":"0"},
    {"$int":"town","value":"0"},
    {"$int":"swim","value":"0"},
    {"$int":"returnMap","value":"910030001"},
    {"$int":"forcedReturn","value":"910030001"},
    {"$float":"mobRate","value":"1.0"},
    {"$string":"bgm","value":"Bgm00/FloralLife"},
    {"$string":"mapMark","value":"Event"},
    {"$int":"fly","value":"0"},
    {"$int":"hideMinimap","value":"0"},
    {"$int":"fieldLimit","value":"1319672"},
    {"$int":"VRTop","value":"-165"},
    {"$int":"VRLeft","value":"-585"},
    {"$int":"VRBottom","value":"570"},
    {"$int":"VRRight","value":"315"},
    {"$string":"onFirstUserEnter","value":""},
    {"$string":"onUserEnter","value":""}
  ]},
  {"$imgdir":"back","$$":[
    {"$imgdir":"0","$$":[
      {"$string":"bS","value":"aquaCave"},
      {"$int":"front","value":"0"},
      {"$int":"ani","value":"0"},
      {"$int":"no","value":"0"},
      {"$int":"f","value":"0"},
      {"$int":"x","value":"0"},
      {"$int":"y","value":"0"},
      {"$int":"rx","value":"-30"},
      {"$int":"ry","value":"-30"},
      {"$int":"type","value":"3"},
      {"$int":"cx","value":"0"},
      {"$int":"cy","value":"0"},
      {"$int":"a","value":"255"}
    ]},
    {"$imgdir":"2","$$":[
      {"$string":"bS","value":"aquaCave"},
      {"$int":"front","value":"0"},
      {"$int":"ani","value":"0"},
      {"$int":"no","value":"6"},
      {"$int":"f","value":"0"},
      {"$int":"x","value":"-193"},
      {"$int":"y","value":"338"},
      {"$int":"rx","value":"-40"},
      {"$int":"ry","value":"-100"},
      {"$int":"type","value":"3"},
      {"$int":"cx","value":"568"},
      {"$int":"cy","value":"700"},
      {"$int":"a","value":"255"}
    ]},
    {"$imgdir":"3","$$":[
      {"$string":"bS","value":"aquaCave"},
      {"$int":"front","value":"0"},
      {"$int":"ani","value":"0"},
      {"$int":"no","value":"7"},
      {"$int":"f","value":"0"},
      {"$int":"x","value":"-103"},
      {"$int":"y","value":"-51"},
      {"$int":"rx","value":"-40"},
      {"$int":"ry","value":"-100"},
      {"$int":"type","value":"3"},
      {"$int":"cx","value":"568"},
      {"$int":"cy","value":"700"},
      {"$int":"a","value":"255"}
    ]},
    {"$imgdir":"4","$$":[
      {"$string":"bS","value":"aquaCave"},
      {"$int":"front","value":"0"},
      {"$int":"ani","value":"0"},
      {"$int":"no","value":"10"},
      {"$int":"f","value":"0"},
      {"$int":"x","value":"38"},
      {"$int":"y","value":"-51"},
      {"$int":"rx","value":"-40"},
      {"$int":"ry","value":"-100"},
      {"$int":"type","value":"3"},
      {"$int":"cx","value":"568"},
      {"$int":"cy","value":"700"},
      {"$int":"a","value":"255"}
    ]},
    {"$imgdir":"6","$$":[
      {"$string":"bS","value":"aquaCave"},
      {"$int":"front","value":"0"},
      {"$int":"ani","value":"0"},
      {"$int":"no","value":"12"},
      {"$int":"f","value":"0"},
      {"$int":"x","value":"127"},
      {"$int":"y","value":"338"},
      {"$int":"rx","value":"-40"},
      {"$int":"ry","value":"-100"},
      {"$int":"type","value":"3"},
      {"$int":"cx","value":"568"},
      {"$int":"cy","value":"700"},
      {"$int":"a","value":"255"}
    ]},
    {"$imgdir":"5","$$":[
      {"$string":"bS","value":"aquaCave"},
      {"$int":"front","value":"0"},
      {"$int":"ani","value":"0"},
      {"$int":"no","value":"11"},
      {"$int":"f","value":"0"},
      {"$int":"x","value":"180"},
      {"$int":"y","value":"47"},
      {"$int":"rx","value":"-40"},
      {"$int":"ry","value":"-100"},
      {"$int":"type","value":"3"},
      {"$int":"cx","value":"568"},
      {"$int":"cy","value":"700"},
      {"$int":"a","value":"255"}
    ]},
    {"$imgdir":"9","$$":[
      {"$string":"bS","value":"aquaCave"},
      {"$int":"front","value":"0"},
      {"$int":"ani","value":"0"},
      {"$int":"no","value":"18"},
      {"$int":"f","value":"0"},
      {"$int":"x","value":"-438"},
      {"$int":"y","value":"-71"},
      {"$int":"rx","value":"-100"},
      {"$int":"ry","value":"-100"},
      {"$int":"type","value":"3"},
      {"$int":"cx","value":"1696"},
      {"$int":"cy","value":"700"},
      {"$int":"a","value":"255"}
    ]},
    {"$imgdir":"10","$$":[
      {"$string":"bS","value":"aquaCave"},
      {"$int":"front","value":"0"},
      {"$int":"ani","value":"0"},
      {"$int":"no","value":"16"},
      {"$int":"f","value":"0"},
      {"$int":"x","value":"-580"},
      {"$int":"y","value":"27"},
      {"$int":"rx","value":"-100"},
      {"$int":"ry","value":"-100"},
      {"$int":"type","value":"3"},
      {"$int":"cx","value":"1696"},
      {"$int":"cy","value":"700"},
      {"$int":"a","value":"255"}
    ]},
    {"$imgdir":"11","$$":[
      {"$string":"bS","value":"aquaCave"},
      {"$int":"front","value":"0"},
      {"$int":"ani","value":"0"},
      {"$int":"no","value":"17"},
      {"$int":"f","value":"0"},
      {"$int":"x","value":"-527"},
      {"$int":"y","value":"318"},
      {"$int":"rx","value":"-100"},
      {"$int":"ry","value":"-100"},
      {"$int":"type","value":"3"},
      {"$int":"cx","value":"1696"},
      {"$int":"cy","value":"700"},
      {"$int":"a","value":"255"}
    ]},
    {"$imgdir":"12","$$":[
      {"$string":"bS","value":"aquaCave"},
      {"$int":"front","value":"0"},
      {"$int":"ani","value":"0"},
      {"$int":"no","value":"21"},
      {"$int":"f","value":"0"},
      {"$int":"x","value":"126"},
      {"$int":"y","value":"-71"},
      {"$int":"rx","value":"-100"},
      {"$int":"ry","value":"-100"},
      {"$int":"type","value":"3"},
      {"$int":"cx","value":"1696"},
      {"$int":"cy","value":"700"},
      {"$int":"a","value":"255"}
    ]},
    {"$imgdir":"13","$$":[
      {"$string":"bS","value":"aquaCave"},
      {"$int":"front","value":"0"},
      {"$int":"ani","value":"0"},
      {"$int":"no","value":"22"},
      {"$int":"f","value":"0"},
      {"$int":"x","value":"268"},
      {"$int":"y","value":"27"},
      {"$int":"rx","value":"-100"},
      {"$int":"ry","value":"-100"},
      {"$int":"type","value":"3"},
      {"$int":"cx","value":"1696"},
      {"$int":"cy","value":"700"},
      {"$int":"a","value":"255"}
    ]},
    {"$imgdir":"14","$$":[
      {"$string":"bS","value":"aquaCave"},
      {"$int":"front","value":"0"},
      {"$int":"ani","value":"0"},
      {"$int":"no","value":"23"},
      {"$int":"f","value":"0"},
      {"$int":"x","value":"216"},
      {"$int":"y","value":"318"},
      {"$int":"rx","value":"-100"},
      {"$int":"ry","value":"-100"},
      {"$int":"type","value":"3"},
      {"$int":"cx","value":"1696"},
      {"$int":"cy","value":"700"},
      {"$int":"a","value":"255"}
    ]},
    {"$imgdir":"15","$$":[
      {"$string":"bS","value":"aquaCave"},
      {"$int":"front","value":"1"},
      {"$int":"ani","value":"0"},
      {"$int":"no","value":"19"},
      {"$int":"f","value":"0"},
      {"$int":"x","value":"-15"},
      {"$int":"y","value":"-91"},
      {"$int":"rx","value":"-100"},
      {"$int":"ry","value":"-100"},
      {"$int":"type","value":"0"},
      {"$int":"cx","value":"0"},
      {"$int":"cy","value":"0"},
      {"$int":"a","value":"255"}
    ]},
    {"$imgdir":"1","$$":[
      {"$string":"bS","value":"aquaCave"},
      {"$int":"front","value":"0"},
      {"$int":"ani","value":"0"},
      {"$int":"no","value":"5"},
      {"$int":"f","value":"0"},
      {"$int":"x","value":"-245"},
      {"$int":"y","value":"47"},
      {"$int":"rx","value":"-40"},
      {"$int":"ry","value":"-100"},
      {"$int":"type","value":"3"},
      {"$int":"cx","value":"568"},
      {"$int":"cy","value":"700"},
      {"$int":"a","value":"255"}
    ]},
    {"$imgdir":"8","$$":[
      {"$string":"bS","value":"aquaCave"},
      {"$int":"front","value":"0"},
      {"$int":"ani","value":"0"},
      {"$int":"no","value":"15"},
      {"$int":"f","value":"0"},
      {"$int":"x","value":"1470"},
      {"$int":"y","value":"-123"},
      {"$int":"rx","value":"-100"},
      {"$int":"ry","value":"-100"},
      {"$int":"type","value":"3"},
      {"$int":"cx","value":"1696"},
      {"$int":"cy","value":"700"},
      {"$int":"a","value":"255"}
    ]},
    {"$imgdir":"7","$$":[
      {"$string":"bS","value":"aquaCave"},
      {"$int":"front","value":"0"},
      {"$int":"ani","value":"0"},
      {"$int":"no","value":"20"},
      {"$int":"f","value":"0"},
      {"$int":"x","value":"690"},
      {"$int":"y","value":"-74"},
      {"$int":"rx","value":"-100"},
      {"$int":"ry","value":"-100"},
      {"$int":"type","value":"3"},
      {"$int":"cx","value":"1696"},
      {"$int":"cy","value":"700"},
      {"$int":"a","value":"255"}
    ]}
  ]},
  {"$imgdir":"life","$$":[
    {"$imgdir":"0","$$":[
      {"$string":"type","value":"n"},
      {"$string":"id","value":"9000047"},
      {"$int":"x","value":"-310"},
      {"$int":"y","value":"398"},
      {"$int":"mobTime","value":"0"},
      {"$int":"f","value":"0"},
      {"$int":"hide","value":"0"},
      {"$int":"fh","value":"3"},
      {"$int":"cy","value":"408"},
      {"$int":"rx0","value":"-360"},
      {"$int":"rx1","value":"-260"}
    ]}
  ]},
  {"$imgdir":"reactor"},
  {"$imgdir":"0","$$":[
    {"$imgdir":"info"},
    {"$imgdir":"tile"},
    {"$imgdir":"obj"}
  ]},
  {"$imgdir":"1","$$":[
    {"$imgdir":"info"},
    {"$imgdir":"tile"},
    {"$imgdir":"obj","$$":[
      {"$imgdir":"1","$$":[
        {"$string":"oS","value":"event"},
        {"$string":"l0","value":"2009winter"},
        {"$string":"l1","value":"pinokio"},
        {"$string":"l2","value":"1"},
        {"$int":"x","value":"-415"},
        {"$int":"y","value":"368"},
        {"$int":"z","value":"9"},
        {"$int":"f","value":"0"},
        {"$int":"zM","value":"5"},
        {"$int":"r","value":"0"}
      ]},
      {"$imgdir":"0","$$":[
        {"$string":"oS","value":"event"},
        {"$string":"l0","value":"2009winter"},
        {"$string":"l1","value":"pinokio"},
        {"$string":"l2","value":"0"},
        {"$int":"x","value":"-178"},
        {"$int":"y","value":"335"},
        {"$int":"z","value":"9"},
        {"$int":"f","value":"0"},
        {"$int":"zM","value":"2"},
        {"$int":"r","value":"0"}
      ]}
    ]}
  ]},
  {"$imgdir":"2","$$":[
    {"$imgdir":"info"},
    {"$imgdir":"tile"},
    {"$imgdir":"obj"}
  ]},
  {"$imgdir":"3","$$":[
    {"$imgdir":"info"},
    {"$imgdir":"tile"},
    {"$imgdir":"obj"}
  ]},
  {"$imgdir":"4","$$":[
    {"$imgdir":"info","$$":[
      {"$string":"tS","value":"deepSeeCave"},
      {"$int":"tSMag","value":"1"}
    ]},
    {"$imgdir":"tile","$$":[
      {"$imgdir":"6","$$":[
        {"$int":"x","value":"-585"},
        {"$int":"y","value":"450"},
        {"$string":"u","value":"bsc"},
        {"$int":"no","value":"0"},
        {"$int":"zM","value":"0"}
      ]},
      {"$imgdir":"2","$$":[
        {"$int":"x","value":"-585"},
        {"$int":"y","value":"450"},
        {"$string":"u","value":"enH0"},
        {"$int":"no","value":"3"},
        {"$int":"zM","value":"0"}
      ]},
      {"$imgdir":"16","$$":[
        {"$int":"x","value":"-495"},
        {"$int":"y","value":"450"},
        {"$string":"u","value":"enH0"},
        {"$int":"no","value":"4"},
        {"$int":"zM","value":"0"}
      ]},
      {"$imgdir":"5","$$":[
        {"$int":"x","value":"-405"},
        {"$int":"y","value":"450"},
        {"$string":"u","value":"enH0"},
        {"$int":"no","value":"0"},
        {"$int":"zM","value":"0"}
      ]},
      {"$imgdir":"0","$$":[
        {"$int":"x","value":"-495"},
        {"$int":"y","value":"450"},
        {"$string":"u","value":"bsc"},
        {"$int":"no","value":"1"},
        {"$int":"zM","value":"0"}
      ]},
      {"$imgdir":"4","$$":[
        {"$int":"x","value":"-405"},
        {"$int":"y","value":"450"},
        {"$string":"u","value":"bsc"},
        {"$int":"no","value":"3"},
        {"$int":"zM","value":"0"}
      ]},
      {"$imgdir":"1","$$":[
        {"$int":"x","value":"-315"},
        {"$int":"y","value":"450"},
        {"$string":"u","value":"bsc"},
        {"$int":"no","value":"1"},
        {"$int":"zM","value":"0"}
      ]},
      {"$imgdir":"13","$$":[
        {"$int":"x","value":"-315"},
        {"$int":"y","value":"450"},
        {"$string":"u","value":"enH0"},
        {"$int":"no","value":"3"},
        {"$int":"zM","value":"0"}
      ]},
      {"$imgdir":"9","$$":[
        {"$int":"x","value":"-585"},
        {"$int":"y","value":"510"},
        {"$string":"u","value":"bsc"},
        {"$int":"no","value":"4"},
        {"$int":"zM","value":"0"}
      ]},
      {"$imgdir":"19","$$":[
        {"$int":"x","value":"-585"},
        {"$int":"y","value":"570"},
        {"$string":"u","value":"enH1"},
        {"$int":"no","value":"0"},
        {"$int":"zM","value":"0"}
      ]},
      {"$imgdir":"7","$$":[
        {"$int":"x","value":"-495"},
        {"$int":"y","value":"510"},
        {"$string":"u","value":"bsc"},
        {"$int":"no","value":"2"},
        {"$int":"zM","value":"0"}
      ]},
      {"$imgdir":"20","$$":[
        {"$int":"x","value":"-495"},
        {"$int":"y","value":"570"},
        {"$string":"u","value":"enH1"},
        {"$int":"no","value":"1"},
        {"$int":"zM","value":"0"}
      ]},
      {"$imgdir":"3","$$":[
        {"$int":"x","value":"-315"},
        {"$int":"y","value":"510"},
        {"$string":"u","value":"bsc"},
        {"$int":"no","value":"2"},
        {"$int":"zM","value":"0"}
      ]},
      {"$imgdir":"15","$$":[
        {"$int":"x","value":"-405"},
        {"$int":"y","value":"510"},
        {"$string":"u","value":"bsc"},
        {"$int":"no","value":"2"},
        {"$int":"zM","value":"0"}
      ]},
      {"$imgdir":"23","$$":[
        {"$int":"x","value":"-405"},
        {"$int":"y","value":"570"},
        {"$string":"u","value":"enH1"},
        {"$int":"no","value":"1"},
        {"$int":"zM","value":"0"}
      ]},
      {"$imgdir":"21","$$":[
        {"$int":"x","value":"-315"},
        {"$int":"y","value":"570"},
        {"$string":"u","value":"enH1"},
        {"$int":"no","value":"1"},
        {"$int":"zM","value":"0"}
      ]},
      {"$imgdir":"28","$$":[
        {"$int":"x","value":"-225"},
        {"$int":"y","value":"450"},
        {"$string":"u","value":"enH0"},
        {"$int":"no","value":"4"},
        {"$int":"zM","value":"0"}
      ]},
      {"$imgdir":"27","$$":[
        {"$int":"x","value":"-135"},
        {"$int":"y","value":"450"},
        {"$string":"u","value":"enH0"},
        {"$int":"no","value":"0"},
        {"$int":"zM","value":"0"}
      ]},
      {"$imgdir":"29","$$":[
        {"$int":"x","value":"-45"},
        {"$int":"y","value":"450"},
        {"$string":"u","value":"enH0"},
        {"$int":"no","value":"3"},
        {"$int":"zM","value":"0"}
      ]},
      {"$imgdir":"26","$$":[
        {"$int":"x","value":"-135"},
        {"$int":"y","value":"450"},
        {"$string":"u","value":"bsc"},
        {"$int":"no","value":"4"},
        {"$int":"zM","value":"0"}
      ]},
      {"$imgdir":"30","$$":[
        {"$int":"x","value":"-45"},
        {"$int":"y","value":"450"},
        {"$string":"u","value":"bsc"},
        {"$int":"no","value":"0"},
        {"$int":"zM","value":"0"}
      ]},
      {"$imgdir":"12","$$":[
        {"$int":"x","value":"-135"},
        {"$int":"y","value":"510"},
        {"$string":"u","value":"bsc"},
        {"$int":"no","value":"1"},
        {"$int":"zM","value":"0"}
      ]},
      {"$imgdir":"17","$$":[
        {"$int":"x","value":"-225"},
        {"$int":"y","value":"510"},
        {"$string":"u","value":"bsc"},
        {"$int":"no","value":"3"},
        {"$int":"zM","value":"0"}
      ]},
      {"$imgdir":"22","$$":[
        {"$int":"x","value":"-225"},
        {"$int":"y","value":"570"},
        {"$string":"u","value":"enH1"},
        {"$int":"no","value":"1"},
        {"$int":"zM","value":"0"}
      ]},
      {"$imgdir":"11","$$":[
        {"$int":"x","value":"-45"},
        {"$int":"y","value":"570"},
        {"$string":"u","value":"enH1"},
        {"$int":"no","value":"2"},
        {"$int":"zM","value":"0"}
      ]},
      {"$imgdir":"10","$$":[
        {"$int":"x","value":"-45"},
        {"$int":"y","value":"510"},
        {"$string":"u","value":"bsc"},
        {"$int":"no","value":"3"},
        {"$int":"zM","value":"0"}
      ]},
      {"$imgdir":"34","$$":[
        {"$int":"x","value":"45"},
        {"$int":"y","value":"510"},
        {"$string":"u","value":"bsc"},
        {"$int":"no","value":"2"},
        {"$int":"zM","value":"0"}
      ]},
      {"$imgdir":"32","$$":[
        {"$int":"x","value":"45"},
        {"$int":"y","value":"450"},
        {"$string":"u","value":"bsc"},
        {"$int":"no","value":"0"},
        {"$int":"zM","value":"0"}
      ]},
      {"$imgdir":"8","$$":[
        {"$int":"x","value":"-225"},
        {"$int":"y","value":"450"},
        {"$string":"u","value":"bsc"},
        {"$int":"no","value":"3"},
        {"$int":"zM","value":"0"}
      ]},
      {"$imgdir":"14","$$":[
        {"$int":"x","value":"45"},
        {"$int":"y","value":"570"},
        {"$string":"u","value":"enH1"},
        {"$int":"no","value":"2"},
        {"$int":"zM","value":"0"}
      ]},
      {"$imgdir":"18","$$":[
        {"$int":"x","value":"-135"},
        {"$int":"y","value":"570"},
        {"$string":"u","value":"enH1"},
        {"$int":"no","value":"0"},
        {"$int":"zM","value":"0"}
      ]},
      {"$imgdir":"35","$$":[
        {"$int":"x","value":"135"},
        {"$int":"y","value":"570"},
        {"$string":"u","value":"enH1"},
        {"$int":"no","value":"2"},
        {"$int":"zM","value":"0"}
      ]},
      {"$imgdir":"24","$$":[
        {"$int":"x","value":"135"},
        {"$int":"y","value":"450"},
        {"$string":"u","value":"bsc"},
        {"$int":"no","value":"1"},
        {"$int":"zM","value":"0"}
      ]},
      {"$imgdir":"25","$$":[
        {"$int":"x","value":"135"},
        {"$int":"y","value":"510"},
        {"$string":"u","value":"bsc"},
        {"$int":"no","value":"2"},
        {"$int":"zM","value":"0"}
      ]},
      {"$imgdir":"43","$$":[
        {"$int":"x","value":"45"},
        {"$int":"y","value":"390"},
        {"$string":"u","value":"edU"},
        {"$int":"no","value":"0"},
        {"$int":"zM","value":"0"}
      ]},
      {"$imgdir":"40","$$":[
        {"$int":"x","value":"45"},
        {"$int":"y","value":"390"},
        {"$string":"u","value":"enV0"},
        {"$int":"no","value":"1"},
        {"$int":"zM","value":"0"}
      ]},
      {"$imgdir":"31","$$":[
        {"$int":"x","value":"45"},
        {"$int":"y","value":"390"},
        {"$string":"u","value":"bsc"},
        {"$int":"no","value":"1"},
        {"$int":"zM","value":"0"}
      ]},
      {"$imgdir":"38","$$":[
        {"$int":"x","value":"45"},
        {"$int":"y","value":"390"},
        {"$string":"u","value":"enH0"},
        {"$int":"no","value":"2"},
        {"$int":"zM","value":"0"}
      ]},
      {"$imgdir":"36","$$":[
        {"$int":"x","value":"225"},
        {"$int":"y","value":"390"},
        {"$string":"u","value":"bsc"},
        {"$int":"no","value":"4"},
        {"$int":"zM","value":"0"}
      ]},
      {"$imgdir":"44","$$":[
        {"$int":"x","value":"225"},
        {"$int":"y","value":"570"},
        {"$string":"u","value":"enH1"},
        {"$int":"no","value":"0"},
        {"$int":"zM","value":"0"}
      ]},
      {"$imgdir":"48","$$":[
        {"$int":"x","value":"225"},
        {"$int":"y","value":"450"},
        {"$string":"u","value":"bsc"},
        {"$int":"no","value":"1"},
        {"$int":"zM","value":"0"}
      ]},
      {"$imgdir":"46","$$":[
        {"$int":"x","value":"225"},
        {"$int":"y","value":"510"},
        {"$string":"u","value":"bsc"},
        {"$int":"no","value":"3"},
        {"$int":"zM","value":"0"}
      ]},
      {"$imgdir":"41","$$":[
        {"$int":"x","value":"135"},
        {"$int":"y","value":"330"},
        {"$string":"u","value":"enV0"},
        {"$int":"no","value":"0"},
        {"$int":"zM","value":"0"}
      ]},
      {"$imgdir":"45","$$":[
        {"$int":"x","value":"225"},
        {"$int":"y","value":"330"},
        {"$string":"u","value":"enH0"},
        {"$int":"no","value":"4"},
        {"$int":"zM","value":"0"}
      ]},
      {"$imgdir":"47","$$":[
        {"$int":"x","value":"225"},
        {"$int":"y","value":"330"},
        {"$string":"u","value":"bsc"},
        {"$int":"no","value":"1"},
        {"$int":"zM","value":"0"}
      ]},
      {"$imgdir":"37","$$":[
        {"$int":"x","value":"135"},
        {"$int":"y","value":"330"},
        {"$string":"u","value":"edU"},
        {"$int":"no","value":"0"},
        {"$int":"zM","value":"0"}
      ]},
      {"$imgdir":"42","$$":[
        {"$int":"x","value":"135"},
        {"$int":"y","value":"390"},
        {"$string":"u","value":"bsc"},
        {"$int":"no","value":"0"},
        {"$int":"zM","value":"0"}
      ]},
      {"$imgdir":"39","$$":[
        {"$int":"x","value":"135"},
        {"$int":"y","value":"330"},
        {"$string":"u","value":"bsc"},
        {"$int":"no","value":"2"},
        {"$int":"zM","value":"0"}
      ]},
      {"$imgdir":"33","$$":[
        {"$int":"x","value":"135"},
        {"$int":"y","value":"330"},
        {"$string":"u","value":"enH0"},
        {"$int":"no","value":"2"},
        {"$int":"zM","value":"0"}
      ]}
    ]},
    {"$imgdir":"obj"}
  ]},
  {"$imgdir":"5","$$":[
    {"$imgdir":"info"},
    {"$imgdir":"tile"},
    {"$imgdir":"obj","$$":[
      {"$imgdir":"0","$$":[
        {"$string":"oS","value":"event"},
        {"$string":"l0","value":"2009winter"},
        {"$string":"l1","value":"pinokio"},
        {"$string":"l2","value":"8"},
        {"$int":"x","value":"-450"},
        {"$int":"y","value":"400"},
        {"$int":"z","value":"9"},
        {"$int":"f","value":"0"},
        {"$int":"zM","value":"3"},
        {"$int":"r","value":"0"}
      ]},
      {"$imgdir":"1","$$":[
        {"$string":"oS","value":"event"},
        {"$string":"l0","value":"2009winter"},
        {"$string":"l1","value":"pinokio"},
        {"$string":"l2","value":"8"},
        {"$int":"x","value":"-180"},
        {"$int":"y","value":"400"},
        {"$int":"z","value":"9"},
        {"$int":"f","value":"0"},
        {"$int":"zM","value":"4"},
        {"$int":"r","value":"0"}
      ]},
      {"$imgdir":"2","$$":[
        {"$string":"oS","value":"event"},
        {"$string":"l0","value":"2009winter"},
        {"$string":"l1","value":"pinokio"},
        {"$string":"l2","value":"7"},
        {"$int":"x","value":"-13"},
        {"$int":"y","value":"438"},
        {"$int":"z","value":"9"},
        {"$int":"f","value":"0"},
        {"$int":"zM","value":"1"},
        {"$int":"r","value":"0"}
      ]},
      {"$imgdir":"3","$$":[
        {"$string":"oS","value":"event"},
        {"$string":"l0","value":"2009winter"},
        {"$string":"l1","value":"pinokio"},
        {"$string":"l2","value":"9"},
        {"$int":"x","value":"270"},
        {"$int":"y","value":"282"},
        {"$int":"z","value":"9"},
        {"$int":"f","value":"0"},
        {"$int":"zM","value":"0"},
        {"$int":"r","value":"0"}
      ]},
      {"$imgdir":"4","$$":[
        {"$string":"oS","value":"event"},
        {"$string":"l0","value":"2009winter"},
        {"$string":"l1","value":"pinokio"},
        {"$string":"l2","value":"9"},
        {"$int":"x","value":"180"},
        {"$int":"y","value":"282"},
        {"$int":"z","value":"9"},
        {"$int":"f","value":"0"},
        {"$int":"zM","value":"0"},
        {"$int":"r","value":"0"}
      ]},
      {"$imgdir":"5","$$":[
        {"$string":"oS","value":"event"},
        {"$string":"l0","value":"2009winter"},
        {"$string":"l1","value":"pinokio"},
        {"$string":"l2","value":"6"},
        {"$int":"x","value":"107"},
        {"$int":"y","value":"316"},
        {"$int":"z","value":"9"},
        {"$int":"f","value":"0"},
        {"$int":"zM","value":"0"},
        {"$int":"r","value":"0"}
      ]},
      {"$imgdir":"6","$$":[
        {"$string":"oS","value":"dungeon3"},
        {"$string":"l0","value":"woodCave"},
        {"$string":"l1","value":"gate"},
        {"$string":"l2","value":"2"},
        {"$int":"x","value":"223"},
        {"$int":"y","value":"215"},
        {"$int":"z","value":"9"},
        {"$int":"f","value":"0"},
        {"$int":"zM","value":"0"},
        {"$int":"r","value":"0"}
      ]}
    ]}
  ]},
  {"$imgdir":"6","$$":[
    {"$imgdir":"info"},
    {"$imgdir":"tile"},
    {"$imgdir":"obj"}
  ]},
  {"$imgdir":"7","$$":[
    {"$imgdir":"info"},
    {"$imgdir":"tile"},
    {"$imgdir":"obj"}
  ]},
  {"$imgdir":"foothold","$$":[
    {"$imgdir":"4","$$":[
      {"$imgdir":"0","$$":[
        {"$imgdir":"1","$$":[
          {"$int":"x1","value":"-585"},
          {"$int":"y1","value":"408"},
          {"$int":"x2","value":"-495"},
          {"$int":"y2","value":"408"},
          {"$int":"prev","value":"0"},
          {"$int":"next","value":"4"}
        ]},
        {"$imgdir":"2","$$":[
          {"$int":"x1","value":"-405"},
          {"$int":"y1","value":"408"},
          {"$int":"x2","value":"-315"},
          {"$int":"y2","value":"408"},
          {"$int":"prev","value":"4"},
          {"$int":"next","value":"3"}
        ]},
        {"$imgdir":"3","$$":[
          {"$int":"x1","value":"-315"},
          {"$int":"y1","value":"408"},
          {"$int":"x2","value":"-225"},
          {"$int":"y2","value":"408"},
          {"$int":"prev","value":"2"},
          {"$int":"next","value":"6"}
        ]},
        {"$imgdir":"4","$$":[
          {"$int":"x1","value":"-495"},
          {"$int":"y1","value":"408"},
          {"$int":"x2","value":"-405"},
          {"$int":"y2","value":"408"},
          {"$int":"prev","value":"1"},
          {"$int":"next","value":"2"}
        ]},
        {"$imgdir":"5","$$":[
          {"$int":"x1","value":"-135"},
          {"$int":"y1","value":"408"},
          {"$int":"x2","value":"-45"},
          {"$int":"y2","value":"408"},
          {"$int":"prev","value":"6"},
          {"$int":"next","value":"7"}
        ]},
        {"$imgdir":"6","$$":[
          {"$int":"x1","value":"-225"},
          {"$int":"y1","value":"408"},
          {"$int":"x2","value":"-135"},
          {"$int":"y2","value":"408"},
          {"$int":"prev","value":"3"},
          {"$int":"next","value":"5"}
        ]},
        {"$imgdir":"7","$$":[
          {"$int":"x1","value":"-45"},
          {"$int":"y1","value":"408"},
          {"$int":"x2","value":"12"},
          {"$int":"y2","value":"408"},
          {"$int":"prev","value":"5"},
          {"$int":"next","value":"13"}
        ]},
        {"$imgdir":"8","$$":[
          {"$int":"x1","value":"135"},
          {"$int":"y1","value":"288"},
          {"$int":"x2","value":"168"},
          {"$int":"y2","value":"288"},
          {"$int":"prev","value":"10"},
          {"$int":"next","value":"11"}
        ]},
        {"$imgdir":"9","$$":[
          {"$int":"x1","value":"102"},
          {"$int":"y1","value":"330"},
          {"$int":"x2","value":"102"},
          {"$int":"y2","value":"288"},
          {"$int":"prev","value":"14"},
          {"$int":"next","value":"10"}
        ]},
        {"$imgdir":"10","$$":[
          {"$int":"x1","value":"102"},
          {"$int":"y1","value":"288"},
          {"$int":"x2","value":"135"},
          {"$int":"y2","value":"288"},
          {"$int":"prev","value":"9"},
          {"$int":"next","value":"8"}
        ]},
        {"$imgdir":"11","$$":[
          {"$int":"x1","value":"168"},
          {"$int":"y1","value":"288"},
          {"$int":"x2","value":"225"},
          {"$int":"y2","value":"288"},
          {"$int":"prev","value":"8"},
          {"$int":"next","value":"18"}
        ]},
        {"$imgdir":"12","$$":[
          {"$int":"x1","value":"45"},
          {"$int":"y1","value":"348"},
          {"$int":"x2","value":"78"},
          {"$int":"y2","value":"348"},
          {"$int":"prev","value":"16"},
          {"$int":"next","value":"17"}
        ]},
        {"$imgdir":"13","$$":[
          {"$int":"x1","value":"12"},
          {"$int":"y1","value":"408"},
          {"$int":"x2","value":"12"},
          {"$int":"y2","value":"390"},
          {"$int":"prev","value":"7"},
          {"$int":"next","value":"15"}
        ]},
        {"$imgdir":"14","$$":[
          {"$int":"x1","value":"102"},
          {"$int":"y1","value":"348"},
          {"$int":"x2","value":"102"},
          {"$int":"y2","value":"330"},
          {"$int":"prev","value":"17"},
          {"$int":"next","value":"9"}
        ]},
        {"$imgdir":"15","$$":[
          {"$int":"x1","value":"12"},
          {"$int":"y1","value":"390"},
          {"$int":"x2","value":"12"},
          {"$int":"y2","value":"348"},
          {"$int":"prev","value":"13"},
          {"$int":"next","value":"16"}
        ]},
        {"$imgdir":"16","$$":[
          {"$int":"x1","value":"12"},
          {"$int":"y1","value":"348"},
          {"$int":"x2","value":"45"},
          {"$int":"y2","value":"348"},
          {"$int":"prev","value":"15"},
          {"$int":"next","value":"12"}
        ]},
        {"$imgdir":"17","$$":[
          {"$int":"x1","value":"78"},
          {"$int":"y1","value":"348"},
          {"$int":"x2","value":"102"},
          {"$int":"y2","value":"348"},
          {"$int":"prev","value":"12"},
          {"$int":"next","value":"14"}
        ]},
        {"$imgdir":"18","$$":[
          {"$int":"x1","value":"225"},
          {"$int":"y1","value":"288"},
          {"$int":"x2","value":"315"},
          {"$int":"y2","value":"288"},
          {"$int":"prev","value":"11"},
          {"$int":"next","value":"0"}
        ]}
      ]}
    ]}
  ]},
  {"$imgdir":"ladderRope"},
  {"$imgdir":"portal","$$":[
    {"$imgdir":"0","$$":[
      {"$string":"pn","value":"sp"},
      {"$int":"pt","value":"0"},
      {"$int":"x","value":"-415"},
      {"$int":"y","value":"388"},
      {"$int":"tm","value":"999999999"},
      {"$string":"tn","value":""}
    ]},
    {"$imgdir":"1","$$":[
      {"$string":"pn","value":"st00"},
      {"$int":"pt","value":"1"},
      {"$int":"x","value":"-506"},
      {"$int":"y","value":"401"},
      {"$int":"tm","value":"999999999"},
      {"$string":"tn","value":""}
    ]},
    {"$imgdir":"2","$$":[
      {"$string":"pn","value":"next00"},
      {"$int":"pt","value":"7"},
      {"$int":"x","value":"215"},
      {"$int":"y","value":"288"},
      {"$int":"tm","value":"999999999"},
      {"$string":"tn","value":""},
      {"$string":"script","value":"pinokio_next"}
    ]}
  ]}
]}