{"$imgdir":"910330001.img","$$":[
  {"$imgdir":"info","$$":[
    {"$int":"version","value":"10"},
    {"$int":"cloud","value":"0"},
    {"$string":"mapDesc","value":""},
    {"$int":"town","value":"0"},
    {"$int":"returnMap","value":"910330001"},
    {"$int":"forcedReturn","value":"910330001"},
    {"$float":"mobRate","value":"2.0"},
    {"$string":"bgm","value":"Bgm03/Subway"},
    {"$int":"hideMinimap","value":"1"},
    {"$int":"moveLimit","value":"0"},
    {"$int":"VRTop","value":"-250"},
    {"$int":"VRLeft","value":"-275"},
    {"$int":"VRBottom","value":"350"},
    {"$int":"VRRight","value":"525"},
    {"$string":"mapMark","value":"KerningCity"},
    {"$int":"fieldLimit","value":"271100"},
    {"$int":"swim","value":"0"},
    {"$int":"fly","value":"0"},
    {"$int":"noMapCmd","value":"0"},
    {"$string":"onFirstUserEnter","value":""},
    {"$string":"onUserEnter","value":""},
    {"$int":"fieldType","value":"24"}
  ]},
  {"$imgdir":"back","$$":[
    {"$imgdir":"0","$$":[
      {"$string":"bS","value":"metroSubway"},
      {"$int":"no","value":"0"},
      {"$int":"x","value":"2"},
      {"$int":"y","value":"-51"},
      {"$int":"rx","value":"-50"},
      {"$int":"ry","value":"-100"},
      {"$int":"type","value":"3"},
      {"$int":"cx","value":"0"},
      {"$int":"cy","value":"900"},
      {"$int":"a","value":"255"},
      {"$int":"front","value":"0"},
      {"$int":"ani","value":"0"},
      {"$int":"f","value":"0"}
    ]},
    {"$imgdir":"1","$$":[
      {"$string":"bS","value":"metroSubway"},
      {"$int":"no","value":"2"},
      {"$int":"x","value":"-126"},
      {"$int":"y","value":"60"},
      {"$int":"rx","value":"-50"},
      {"$int":"ry","value":"-100"},
      {"$int":"type","value":"3"},
      {"$int":"cx","value":"700"},
      {"$int":"cy","value":"900"},
      {"$int":"a","value":"255"},
      {"$int":"front","value":"0"},
      {"$int":"ani","value":"0"},
      {"$int":"f","value":"0"}
    ]},
    {"$imgdir":"2","$$":[
      {"$string":"bS","value":"metroSubway"},
      {"$int":"no","value":"8"},
      {"$int":"x","value":"-299"},
      {"$int":"y","value":"25"},
      {"$int":"rx","value":"-50"},
      {"$int":"ry","value":"-100"},
      {"$int":"type","value":"3"},
      {"$int":"cx","value":"700"},
      {"$int":"cy","value":"900"},
      {"$int":"a","value":"255"},
      {"$int":"front","value":"0"},
      {"$int":"ani","value":"0"},
      {"$int":"f","value":"0"}
    ]},
    {"$imgdir":"4","$$":[
      {"$string":"bS","value":"metroSubway"},
      {"$int":"no","value":"6"},
      {"$int":"x","value":"-198"},
      {"$int":"y","value":"-177"},
      {"$int":"rx","value":"-50"},
      {"$int":"ry","value":"-100"},
      {"$int":"type","value":"3"},
      {"$int":"cx","value":"0"},
      {"$int":"cy","value":"900"},
      {"$int":"a","value":"255"},
      {"$int":"front","value":"0"},
      {"$int":"ani","value":"0"},
      {"$int":"f","value":"0"}
    ]},
    {"$imgdir":"3","$$":[
      {"$string":"bS","value":"metroSubway"},
      {"$int":"no","value":"7"},
      {"$int":"x","value":"-201"},
      {"$int":"y","value":"-188"},
      {"$int":"rx","value":"-50"},
      {"$int":"ry","value":"-100"},
      {"$int":"type","value":"3"},
      {"$int":"cx","value":"700"},
      {"$int":"cy","value":"900"},
      {"$int":"a","value":"255"},
      {"$int":"front","value":"0"},
      {"$int":"ani","value":"0"},
      {"$int":"f","value":"0"}
    ]},
    {"$imgdir":"5","$$":[
      {"$string":"bS","value":"metroSubway"},
      {"$int":"no","value":"3"},
      {"$int":"x","value":"-314"},
      {"$int":"y","value":"124"},
      {"$int":"rx","value":"-50"},
      {"$int":"ry","value":"-100"},
      {"$int":"type","value":"3"},
      {"$int":"cx","value":"0"},
      {"$int":"cy","value":"900"},
      {"$int":"a","value":"255"},
      {"$int":"front","value":"0"},
      {"$int":"ani","value":"0"},
      {"$int":"f","value":"0"}
    ]},
    {"$imgdir":"6","$$":[
      {"$string":"bS","value":"metroSubway"},
      {"$int":"no","value":"1"},
      {"$int":"x","value":"-307"},
      {"$int":"y","value":"183"},
      {"$int":"rx","value":"-50"},
      {"$int":"ry","value":"-100"},
      {"$int":"type","value":"3"},
      {"$int":"cx","value":"0"},
      {"$int":"cy","value":"900"},
      {"$int":"a","value":"255"},
      {"$int":"front","value":"0"},
      {"$int":"ani","value":"0"},
      {"$int":"f","value":"0"}
    ]},
    {"$imgdir":"7","$$":[
      {"$string":"bS","value":"metroSubway"},
      {"$int":"no","value":"10"},
      {"$int":"x","value":"-108"},
      {"$int":"y","value":"-254"},
      {"$int":"rx","value":"-50"},
      {"$int":"ry","value":"-100"},
      {"$int":"type","value":"3"},
      {"$int":"cx","value":"0"},
      {"$int":"cy","value":"900"},
      {"$int":"a","value":"255"},
      {"$int":"front","value":"0"},
      {"$int":"ani","value":"0"},
      {"$int":"f","value":"0"}
    ]},
    {"$imgdir":"8","$$":[
      {"$string":"bS","value":"metroSubway"},
      {"$int":"no","value":"11"},
      {"$int":"x","value":"16"},
      {"$int":"y","value":"-179"},
      {"$int":"rx","value":"-80"},
      {"$int":"ry","value":"-100"},
      {"$int":"type","value":"3"},
      {"$int":"cx","value":"600"},
      {"$int":"cy","value":"900"},
      {"$int":"a","value":"255"},
      {"$int":"front","value":"0"},
      {"$int":"ani","value":"0"},
      {"$int":"f","value":"0"}
    ]},
    {"$imgdir":"9","$$":[
      {"$string":"bS","value":"metroSubway"},
      {"$int":"no","value":"12"},
      {"$int":"x","value":"-107"},
      {"$int":"y","value":"-107"},
      {"$int":"rx","value":"-80"},
      {"$int":"ry","value":"-100"},
      {"$int":"type","value":"3"},
      {"$int":"cx","value":"0"},
      {"$int":"cy","value":"900"},
      {"$int":"a","value":"255"},
      {"$int":"front","value":"0"},
      {"$int":"ani","value":"0"},
      {"$int":"f","value":"0"}
    ]},
    {"$imgdir":"10","$$":[
      {"$string":"bS","value":"metroSubway"},
      {"$int":"no","value":"13"},
      {"$int":"x","value":"-152"},
      {"$int":"y","value":"-34"},
      {"$int":"rx","value":"-100"},
      {"$int":"ry","value":"-100"},
      {"$int":"type","value":"3"},
      {"$int":"cx","value":"400"},
      {"$int":"cy","value":"900"},
      {"$int":"a","value":"255"},
      {"$int":"front","value":"0"},
      {"$int":"ani","value":"0"},
      {"$int":"f","value":"0"}
    ]}
  ]},
  {"$imgdir":"life","$$":[
    {"$imgdir":"0","$$":[
      {"$string":"type","value":"n"},
      {"$string":"id","value":"1052115"},
      {"$int":"x","value":"406"},
      {"$int":"y","value":"177"},
      {"$int":"mobTime","value":"0"},
      {"$int":"f","value":"0"},
      {"$int":"hide","value":"0"},
      {"$int":"fh","value":"28"},
      {"$int":"cy","value":"182"},
      {"$int":"rx0","value":"356"},
      {"$int":"rx1","value":"456"}
    ]}
  ]},
  {"$imgdir":"0","$$":[
    {"$imgdir":"info"},
    {"$imgdir":"tile"},
    {"$imgdir":"obj"}
  ]},
  {"$imgdir":"1","$$":[
    {"$imgdir":"info"},
    {"$imgdir":"tile"},
    {"$imgdir":"obj","$$":[
      {"$imgdir":"1","$$":[
        {"$string":"oS","value":"dungeon"},
        {"$string":"l0","value":"metroSubway"},
        {"$string":"l1","value":"acc"},
        {"$string":"l2","value":"7"},
        {"$int":"x","value":"202"},
        {"$int":"y","value":"136"},
        {"$int":"z","value":"9"},
        {"$int":"f","value":"0"},
        {"$int":"zM","value":"4"},
        {"$int":"r","value":"0"}
      ]},
      {"$imgdir":"2","$$":[
        {"$string":"oS","value":"dungeon"},
        {"$string":"l0","value":"metroSubway"},
        {"$string":"l1","value":"acc"},
        {"$string":"l2","value":"12"},
        {"$int":"x","value":"-206"},
        {"$int":"y","value":"170"},
        {"$int":"z","value":"9"},
        {"$int":"f","value":"0"},
        {"$int":"zM","value":"3"},
        {"$int":"r","value":"0"}
      ]},
      {"$imgdir":"0","$$":[
        {"$string":"oS","value":"dungeon"},
        {"$string":"l0","value":"metroSubway"},
        {"$string":"l1","value":"acc"},
        {"$string":"l2","value":"15"},
        {"$int":"x","value":"-188"},
        {"$int":"y","value":"-179"},
        {"$int":"z","value":"9"},
        {"$int":"f","value":"0"},
        {"$int":"zM","value":"6"},
        {"$int":"r","value":"0"}
      ]}
    ]}
  ]},
  {"$imgdir":"2","$$":[
    {"$imgdir":"info"},
    {"$imgdir":"tile"},
    {"$imgdir":"obj"}
  ]},
  {"$imgdir":"3","$$":[
    {"$imgdir":"info"},
    {"$imgdir":"tile"},
    {"$imgdir":"obj"}
  ]},
  {"$imgdir":"4","$$":[
    {"$imgdir":"info"},
    {"$imgdir":"tile"},
    {"$imgdir":"obj"}
  ]},
  {"$imgdir":"5","$$":[
    {"$imgdir":"info","$$":[
      {"$string":"tS","value":"rustSubway"},
      {"$int":"tSMag","value":"1"}
    ]},
    {"$imgdir":"tile","$$":[
      {"$imgdir":"7","$$":[
        {"$int":"x","value":"-360"},
        {"$int":"y","value":"180"},
        {"$string":"u","value":"bsc"},
        {"$int":"no","value":"0"},
        {"$int":"zM","value":"0"}
      ]},
      {"$imgdir":"19","$$":[
        {"$int":"x","value":"-270"},
        {"$int":"y","value":"180"},
        {"$string":"u","value":"enV1"},
        {"$int":"no","value":"1"},
        {"$int":"zM","value":"0"}
      ]},
      {"$imgdir":"5","$$":[
        {"$int":"x","value":"-360"},
        {"$int":"y","value":"60"},
        {"$string":"u","value":"bsc"},
        {"$int":"no","value":"0"},
        {"$int":"zM","value":"0"}
      ]},
      {"$imgdir":"11","$$":[
        {"$int":"x","value":"-360"},
        {"$int":"y","value":"120"},
        {"$string":"u","value":"bsc"},
        {"$int":"no","value":"0"},
        {"$int":"zM","value":"0"}
      ]},
      {"$imgdir":"15","$$":[
        {"$int":"x","value":"-270"},
        {"$int":"y","value":"120"},
        {"$string":"u","value":"enV1"},
        {"$int":"no","value":"0"},
        {"$int":"zM","value":"0"}
      ]},
      {"$imgdir":"8","$$":[
        {"$int":"x","value":"-270"},
        {"$int":"y","value":"60"},
        {"$string":"u","value":"enV1"},
        {"$int":"no","value":"1"},
        {"$int":"zM","value":"0"}
      ]},
      {"$imgdir":"13","$$":[
        {"$int":"x","value":"-360"},
        {"$int":"y","value":"0"},
        {"$string":"u","value":"bsc"},
        {"$int":"no","value":"0"},
        {"$int":"zM","value":"0"}
      ]},
      {"$imgdir":"1","$$":[
        {"$int":"x","value":"-360"},
        {"$int":"y","value":"-120"},
        {"$string":"u","value":"bsc"},
        {"$int":"no","value":"0"},
        {"$int":"zM","value":"0"}
      ]},
      {"$imgdir":"6","$$":[
        {"$int":"x","value":"-270"},
        {"$int":"y","value":"-120"},
        {"$string":"u","value":"enV1"},
        {"$int":"no","value":"0"},
        {"$int":"zM","value":"0"}
      ]},
      {"$imgdir":"17","$$":[
        {"$int":"x","value":"-270"},
        {"$int":"y","value":"-180"},
        {"$string":"u","value":"enV1"},
        {"$int":"no","value":"0"},
        {"$int":"zM","value":"0"}
      ]},
      {"$imgdir":"2","$$":[
        {"$int":"x","value":"-270"},
        {"$int":"y","value":"-300"},
        {"$string":"u","value":"enV1"},
        {"$int":"no","value":"0"},
        {"$int":"zM","value":"0"}
      ]},
      {"$imgdir":"4","$$":[
        {"$int":"x","value":"-360"},
        {"$int":"y","value":"-240"},
        {"$string":"u","value":"bsc"},
        {"$int":"no","value":"0"},
        {"$int":"zM","value":"0"}
      ]},
      {"$imgdir":"21","$$":[
        {"$int":"x","value":"-360"},
        {"$int":"y","value":"-300"},
        {"$string":"u","value":"bsc"},
        {"$int":"no","value":"0"},
        {"$int":"zM","value":"0"}
      ]},
      {"$imgdir":"0","$$":[
        {"$int":"x","value":"-270"},
        {"$int":"y","value":"-240"},
        {"$string":"u","value":"enV1"},
        {"$int":"no","value":"1"},
        {"$int":"zM","value":"0"}
      ]},
      {"$imgdir":"14","$$":[
        {"$int":"x","value":"-360"},
        {"$int":"y","value":"-180"},
        {"$string":"u","value":"bsc"},
        {"$int":"no","value":"0"},
        {"$int":"zM","value":"0"}
      ]},
      {"$imgdir":"9","$$":[
        {"$int":"x","value":"-270"},
        {"$int":"y","value":"240"},
        {"$string":"u","value":"enV1"},
        {"$int":"no","value":"0"},
        {"$int":"zM","value":"0"}
      ]},
      {"$imgdir":"18","$$":[
        {"$int":"x","value":"-360"},
        {"$int":"y","value":"240"},
        {"$string":"u","value":"bsc"},
        {"$int":"no","value":"0"},
        {"$int":"zM","value":"0"}
      ]},
      {"$imgdir":"16","$$":[
        {"$int":"x","value":"-360"},
        {"$int":"y","value":"300"},
        {"$string":"u","value":"bsc"},
        {"$int":"no","value":"0"},
        {"$int":"zM","value":"0"}
      ]},
      {"$imgdir":"20","$$":[
        {"$int":"x","value":"-270"},
        {"$int":"y","value":"300"},
        {"$string":"u","value":"enV1"},
        {"$int":"no","value":"1"},
        {"$int":"zM","value":"0"}
      ]},
      {"$imgdir":"3","$$":[
        {"$int":"x","value":"-270"},
        {"$int":"y","value":"0"},
        {"$string":"u","value":"enV1"},
        {"$int":"no","value":"1"},
        {"$int":"zM","value":"0"}
      ]},
      {"$imgdir":"10","$$":[
        {"$int":"x","value":"-360"},
        {"$int":"y","value":"-60"},
        {"$string":"u","value":"bsc"},
        {"$int":"no","value":"0"},
        {"$int":"zM","value":"0"}
      ]},
      {"$imgdir":"26","$$":[
        {"$int":"x","value":"540"},
        {"$int":"y","value":"180"},
        {"$string":"u","value":"enV0"},
        {"$int":"no","value":"0"},
        {"$int":"zM","value":"1"}
      ]},
      {"$imgdir":"30","$$":[
        {"$int":"x","value":"540"},
        {"$int":"y","value":"240"},
        {"$string":"u","value":"enV0"},
        {"$int":"no","value":"0"},
        {"$int":"zM","value":"1"}
      ]},
      {"$imgdir":"32","$$":[
        {"$int":"x","value":"540"},
        {"$int":"y","value":"300"},
        {"$string":"u","value":"enV0"},
        {"$int":"no","value":"0"},
        {"$int":"zM","value":"1"}
      ]},
      {"$imgdir":"37","$$":[
        {"$int":"x","value":"540"},
        {"$int":"y","value":"300"},
        {"$string":"u","value":"bsc"},
        {"$int":"no","value":"0"},
        {"$int":"zM","value":"1"}
      ]},
      {"$imgdir":"27","$$":[
        {"$int":"x","value":"540"},
        {"$int":"y","value":"240"},
        {"$string":"u","value":"bsc"},
        {"$int":"no","value":"0"},
        {"$int":"zM","value":"1"}
      ]},
      {"$imgdir":"34","$$":[
        {"$int":"x","value":"540"},
        {"$int":"y","value":"180"},
        {"$string":"u","value":"bsc"},
        {"$int":"no","value":"0"},
        {"$int":"zM","value":"1"}
      ]},
      {"$imgdir":"28","$$":[
        {"$int":"x","value":"540"},
        {"$int":"y","value":"120"},
        {"$string":"u","value":"enV0"},
        {"$int":"no","value":"0"},
        {"$int":"zM","value":"1"}
      ]},
      {"$imgdir":"29","$$":[
        {"$int":"x","value":"540"},
        {"$int":"y","value":"120"},
        {"$string":"u","value":"bsc"},
        {"$int":"no","value":"0"},
        {"$int":"zM","value":"1"}
      ]},
      {"$imgdir":"36","$$":[
        {"$int":"x","value":"540"},
        {"$int":"y","value":"60"},
        {"$string":"u","value":"enV0"},
        {"$int":"no","value":"1"},
        {"$int":"zM","value":"1"}
      ]},
      {"$imgdir":"41","$$":[
        {"$int":"x","value":"540"},
        {"$int":"y","value":"60"},
        {"$string":"u","value":"bsc"},
        {"$int":"no","value":"0"},
        {"$int":"zM","value":"1"}
      ]},
      {"$imgdir":"43","$$":[
        {"$int":"x","value":"540"},
        {"$int":"y","value":"-120"},
        {"$string":"u","value":"bsc"},
        {"$int":"no","value":"0"},
        {"$int":"zM","value":"1"}
      ]},
      {"$imgdir":"42","$$":[
        {"$int":"x","value":"540"},
        {"$int":"y","value":"-180"},
        {"$string":"u","value":"bsc"},
        {"$int":"no","value":"0"},
        {"$int":"zM","value":"1"}
      ]},
      {"$imgdir":"39","$$":[
        {"$int":"x","value":"540"},
        {"$int":"y","value":"-240"},
        {"$string":"u","value":"bsc"},
        {"$int":"no","value":"0"},
        {"$int":"zM","value":"1"}
      ]},
      {"$imgdir":"40","$$":[
        {"$int":"x","value":"540"},
        {"$int":"y","value":"-180"},
        {"$string":"u","value":"enV0"},
        {"$int":"no","value":"0"},
        {"$int":"zM","value":"1"}
      ]},
      {"$imgdir":"35","$$":[
        {"$int":"x","value":"540"},
        {"$int":"y","value":"-300"},
        {"$string":"u","value":"bsc"},
        {"$int":"no","value":"0"},
        {"$int":"zM","value":"1"}
      ]},
      {"$imgdir":"31","$$":[
        {"$int":"x","value":"540"},
        {"$int":"y","value":"-120"},
        {"$string":"u","value":"enV0"},
        {"$int":"no","value":"0"},
        {"$int":"zM","value":"1"}
      ]},
      {"$imgdir":"38","$$":[
        {"$int":"x","value":"540"},
        {"$int":"y","value":"-60"},
        {"$string":"u","value":"enV0"},
        {"$int":"no","value":"0"},
        {"$int":"zM","value":"1"}
      ]},
      {"$imgdir":"33","$$":[
        {"$int":"x","value":"540"},
        {"$int":"y","value":"-240"},
        {"$string":"u","value":"enV0"},
        {"$int":"no","value":"0"},
        {"$int":"zM","value":"1"}
      ]},
      {"$imgdir":"22","$$":[
        {"$int":"x","value":"-270"},
        {"$int":"y","value":"-60"},
        {"$string":"u","value":"enV1"},
        {"$int":"no","value":"1"},
        {"$int":"zM","value":"0"}
      ]},
      {"$imgdir":"23","$$":[
        {"$int":"x","value":"540"},
        {"$int":"y","value":"-300"},
        {"$string":"u","value":"enV0"},
        {"$int":"no","value":"1"},
        {"$int":"zM","value":"1"}
      ]},
      {"$imgdir":"25","$$":[
        {"$int":"x","value":"540"},
        {"$int":"y","value":"0"},
        {"$string":"u","value":"bsc"},
        {"$int":"no","value":"0"},
        {"$int":"zM","value":"1"}
      ]},
      {"$imgdir":"24","$$":[
        {"$int":"x","value":"540"},
        {"$int":"y","value":"0"},
        {"$string":"u","value":"enV0"},
        {"$int":"no","value":"0"},
        {"$int":"zM","value":"1"}
      ]},
      {"$imgdir":"12","$$":[
        {"$int":"x","value":"540"},
        {"$int":"y","value":"-60"},
        {"$string":"u","value":"bsc"},
        {"$int":"no","value":"0"},
        {"$int":"zM","value":"1"}
      ]}
    ]},
    {"$imgdir":"obj","$$":[
      {"$imgdir":"1","$$":[
        {"$string":"oS","value":"dungeon"},
        {"$string":"l0","value":"metroSubway"},
        {"$string":"l1","value":"foot"},
        {"$string":"l2","value":"0"},
        {"$int":"x","value":"-94"},
        {"$int":"y","value":"284"},
        {"$int":"z","value":"3"},
        {"$int":"f","value":"0"},
        {"$int":"zM","value":"2"},
        {"$int":"forbidFallDown","value":"1"}
      ]},
      {"$imgdir":"0","$$":[
        {"$string":"oS","value":"dungeon"},
        {"$string":"l0","value":"metroSubway"},
        {"$string":"l1","value":"foot"},
        {"$string":"l2","value":"0"},
        {"$int":"x","value":"253"},
        {"$int":"y","value":"284"},
        {"$int":"z","value":"9"},
        {"$int":"f","value":"0"},
        {"$int":"zM","value":"2"},
        {"$int":"forbidFallDown","value":"1"}
      ]},
      {"$imgdir":"3","$$":[
        {"$string":"oS","value":"dungeon"},
        {"$string":"l0","value":"metroSubway"},
        {"$string":"l1","value":"gate"},
        {"$string":"l2","value":"1"},
        {"$int":"x","value":"350"},
        {"$int":"y","value":"-174"},
        {"$int":"z","value":"7"},
        {"$int":"f","value":"0"},
        {"$int":"zM","value":"5"},
        {"$int":"r","value":"0"}
      ]},
      {"$imgdir":"4","$$":[
        {"$string":"oS","value":"dungeon"},
        {"$string":"l0","value":"metroSubway"},
        {"$string":"l1","value":"acc"},
        {"$string":"l2","value":"16"},
        {"$int":"x","value":"436"},
        {"$int":"y","value":"-187"},
        {"$int":"z","value":"9"},
        {"$int":"f","value":"1"},
        {"$int":"zM","value":"5"},
        {"$int":"r","value":"0"}
      ]},
      {"$imgdir":"5","$$":[
        {"$string":"oS","value":"dungeon"},
        {"$string":"l0","value":"metroSubway"},
        {"$string":"l1","value":"acc"},
        {"$string":"l2","value":"17"},
        {"$int":"x","value":"411"},
        {"$int":"y","value":"58"},
        {"$int":"z","value":"9"},
        {"$int":"f","value":"0"},
        {"$int":"zM","value":"2"},
        {"$int":"r","value":"0"}
      ]},
      {"$imgdir":"6","$$":[
        {"$string":"oS","value":"dungeon"},
        {"$string":"l0","value":"metroSubway"},
        {"$string":"l1","value":"foot"},
        {"$string":"l2","value":"0"},
        {"$int":"x","value":"379"},
        {"$int":"y","value":"284"},
        {"$int":"z","value":"4"},
        {"$int":"f","value":"0"},
        {"$int":"zM","value":"2"},
        {"$int":"r","value":"0"},
        {"$int":"forbidFallDown","value":"1"}
      ]},
      {"$imgdir":"7","$$":[
        {"$string":"oS","value":"dungeon"},
        {"$string":"l0","value":"metroSubway"},
        {"$string":"l1","value":"gate"},
        {"$string":"l2","value":"3"},
        {"$int":"x","value":"-233"},
        {"$int":"y","value":"160"},
        {"$int":"z","value":"0"},
        {"$int":"f","value":"0"},
        {"$int":"zM","value":"2"},
        {"$int":"r","value":"0"}
      ]},
      {"$imgdir":"2","$$":[
        {"$string":"oS","value":"dungeon"},
        {"$string":"l0","value":"metroSubway"},
        {"$string":"l1","value":"gate"},
        {"$string":"l2","value":"2"},
        {"$int":"x","value":"424"},
        {"$int":"y","value":"89"},
        {"$int":"z","value":"9"},
        {"$int":"f","value":"0"},
        {"$int":"zM","value":"2"},
        {"$int":"r","value":"0"}
      ]}
    ]}
  ]},
  {"$imgdir":"6","$$":[
    {"$imgdir":"info"},
    {"$imgdir":"tile"},
    {"$imgdir":"obj"}
  ]},
  {"$imgdir":"7","$$":[
    {"$imgdir":"info"},
    {"$imgdir":"tile"},
    {"$imgdir":"obj"}
  ]},
  {"$imgdir":"reactor"},
  {"$imgdir":"mobMassacre","$$":[
    {"$int":"mapDistance","value":"100"},
    {"$imgdir":"gauge","$$":[
      {"$int":"total","value":"100"},
      {"$int":"decrease","value":"4"},
      {"$int":"coolAdd","value":"2"},
      {"$int":"missSub","value":"3"}
    ]},
    {"$imgdir":"countEffect"}
  ]},
  {"$imgdir":"user","$$":[
    {"$imgdir":"0","$$":[
      {"$imgdir":"cond","$$":[
        {"$int":"jobCategory","value":"1"},
        {"$int":"level","value":"24"},
        {"$int":"compare","value":"1"}
      ]},
      {"$imgdir":"stat","$$":[
        {"$int":"acc","value":"40"}
      ]}
    ]},
    {"$imgdir":"1","$$":[
      {"$imgdir":"cond","$$":[
        {"$int":"jobCategory","value":"11"},
        {"$int":"level","value":"24"},
        {"$int":"compare","value":"1"}
      ]},
      {"$imgdir":"stat","$$":[
        {"$int":"acc","value":"40"}
      ]}
    ]},
    {"$imgdir":"2","$$":[
      {"$imgdir":"cond","$$":[
        {"$int":"jobCategory","value":"21"},
        {"$int":"level","value":"24"},
        {"$int":"compare","value":"1"}
      ]},
      {"$imgdir":"stat","$$":[
        {"$int":"acc","value":"40"}
      ]}
    ]}
  ]},
  {"$imgdir":"foothold","$$":[
    {"$imgdir":"5","$$":[
      {"$imgdir":"0","$$":[
        {"$imgdir":"1","$$":[
          {"$int":"x1","value":"-250"},
          {"$int":"y1","value":"-240"},
          {"$int":"x2","value":"-250"},
          {"$int":"y2","value":"-180"},
          {"$int":"prev","value":"2"},
          {"$int":"next","value":"8"}
        ]},
        {"$imgdir":"2","$$":[
          {"$int":"x1","value":"-250"},
          {"$int":"y1","value":"-300"},
          {"$int":"x2","value":"-250"},
          {"$int":"y2","value":"-240"},
          {"$int":"prev","value":"0"},
          {"$int":"next","value":"1"}
        ]},
        {"$imgdir":"3","$$":[
          {"$int":"x1","value":"-250"},
          {"$int":"y1","value":"0"},
          {"$int":"x2","value":"-250"},
          {"$int":"y2","value":"60"},
          {"$int":"prev","value":"11"},
          {"$int":"next","value":"5"}
        ]},
        {"$imgdir":"4","$$":[
          {"$int":"x1","value":"-250"},
          {"$int":"y1","value":"-120"},
          {"$int":"x2","value":"-250"},
          {"$int":"y2","value":"-60"},
          {"$int":"prev","value":"8"},
          {"$int":"next","value":"11"}
        ]},
        {"$imgdir":"5","$$":[
          {"$int":"x1","value":"-250"},
          {"$int":"y1","value":"60"},
          {"$int":"x2","value":"-250"},
          {"$int":"y2","value":"120"},
          {"$int":"prev","value":"3"},
          {"$int":"next","value":"7"}
        ]},
        {"$imgdir":"6","$$":[
          {"$int":"x1","value":"-250"},
          {"$int":"y1","value":"240"},
          {"$int":"x2","value":"-250"},
          {"$int":"y2","value":"300"},
          {"$int":"prev","value":"12"},
          {"$int":"next","value":"10"}
        ]},
        {"$imgdir":"7","$$":[
          {"$int":"x1","value":"-250"},
          {"$int":"y1","value":"120"},
          {"$int":"x2","value":"-250"},
          {"$int":"y2","value":"180"},
          {"$int":"prev","value":"5"},
          {"$int":"next","value":"9"}
        ]},
        {"$imgdir":"8","$$":[
          {"$int":"x1","value":"-250"},
          {"$int":"y1","value":"-180"},
          {"$int":"x2","value":"-250"},
          {"$int":"y2","value":"-120"},
          {"$int":"prev","value":"1"},
          {"$int":"next","value":"4"}
        ]},
        {"$imgdir":"9","$$":[
          {"$int":"x1","value":"-250"},
          {"$int":"y1","value":"180"},
          {"$int":"x2","value":"-250"},
          {"$int":"y2","value":"218"},
          {"$int":"prev","value":"7"},
          {"$int":"next","value":"26"}
        ]},
        {"$imgdir":"10","$$":[
          {"$int":"x1","value":"-250"},
          {"$int":"y1","value":"300"},
          {"$int":"x2","value":"-250"},
          {"$int":"y2","value":"360"},
          {"$int":"prev","value":"6"},
          {"$int":"next","value":"0"}
        ]},
        {"$imgdir":"11","$$":[
          {"$int":"x1","value":"-250"},
          {"$int":"y1","value":"-60"},
          {"$int":"x2","value":"-250"},
          {"$int":"y2","value":"0"},
          {"$int":"prev","value":"4"},
          {"$int":"next","value":"3"}
        ]},
        {"$imgdir":"12","$$":[
          {"$int":"x1","value":"-250"},
          {"$int":"y1","value":"218"},
          {"$int":"x2","value":"-250"},
          {"$int":"y2","value":"240"},
          {"$int":"prev","value":"9"},
          {"$int":"next","value":"6"}
        ]}
      ]},
      {"$imgdir":"1","$$":[
        {"$imgdir":"13","$$":[
          {"$int":"x1","value":"495"},
          {"$int":"y1","value":"-240"},
          {"$int":"x2","value":"495"},
          {"$int":"y2","value":"-300"},
          {"$int":"prev","value":"20"},
          {"$int":"next","value":"0"}
        ]},
        {"$imgdir":"14","$$":[
          {"$int":"x1","value":"495"},
          {"$int":"y1","value":"60"},
          {"$int":"x2","value":"495"},
          {"$int":"y2","value":"0"},
          {"$int":"prev","value":"21"},
          {"$int":"next","value":"22"}
        ]},
        {"$imgdir":"15","$$":[
          {"$int":"x1","value":"495"},
          {"$int":"y1","value":"240"},
          {"$int":"x2","value":"495"},
          {"$int":"y2","value":"218"},
          {"$int":"prev","value":"17"},
          {"$int":"next","value":"24"}
        ]},
        {"$imgdir":"16","$$":[
          {"$int":"x1","value":"495"},
          {"$int":"y1","value":"180"},
          {"$int":"x2","value":"495"},
          {"$int":"y2","value":"120"},
          {"$int":"prev","value":"24"},
          {"$int":"next","value":"21"}
        ]},
        {"$imgdir":"17","$$":[
          {"$int":"x1","value":"495"},
          {"$int":"y1","value":"300"},
          {"$int":"x2","value":"495"},
          {"$int":"y2","value":"240"},
          {"$int":"prev","value":"19"},
          {"$int":"next","value":"15"}
        ]},
        {"$imgdir":"18","$$":[
          {"$int":"x1","value":"495"},
          {"$int":"y1","value":"-60"},
          {"$int":"x2","value":"495"},
          {"$int":"y2","value":"-120"},
          {"$int":"prev","value":"22"},
          {"$int":"next","value":"23"}
        ]},
        {"$imgdir":"19","$$":[
          {"$int":"x1","value":"495"},
          {"$int":"y1","value":"360"},
          {"$int":"x2","value":"495"},
          {"$int":"y2","value":"300"},
          {"$int":"prev","value":"0"},
          {"$int":"next","value":"17"}
        ]},
        {"$imgdir":"20","$$":[
          {"$int":"x1","value":"495"},
          {"$int":"y1","value":"-180"},
          {"$int":"x2","value":"495"},
          {"$int":"y2","value":"-240"},
          {"$int":"prev","value":"23"},
          {"$int":"next","value":"13"}
        ]},
        {"$imgdir":"21","$$":[
          {"$int":"x1","value":"495"},
          {"$int":"y1","value":"120"},
          {"$int":"x2","value":"495"},
          {"$int":"y2","value":"60"},
          {"$int":"prev","value":"16"},
          {"$int":"next","value":"14"}
        ]},
        {"$imgdir":"22","$$":[
          {"$int":"x1","value":"495"},
          {"$int":"y1","value":"0"},
          {"$int":"x2","value":"495"},
          {"$int":"y2","value":"-60"},
          {"$int":"prev","value":"14"},
          {"$int":"next","value":"18"}
        ]},
        {"$imgdir":"23","$$":[
          {"$int":"x1","value":"495"},
          {"$int":"y1","value":"-120"},
          {"$int":"x2","value":"495"},
          {"$int":"y2","value":"-180"},
          {"$int":"prev","value":"18"},
          {"$int":"next","value":"20"}
        ]},
        {"$imgdir":"24","$$":[
          {"$int":"x1","value":"495"},
          {"$int":"y1","value":"218"},
          {"$int":"x2","value":"495"},
          {"$int":"y2","value":"180"},
          {"$int":"prev","value":"29"},
          {"$int":"next","value":"16"}
        ]}
      ]},
      {"$imgdir":"2","$$":[
        {"$imgdir":"25","$$":[
          {"$int":"x1","value":"75"},
          {"$int":"y1","value":"218"},
          {"$int":"x2","value":"432"},
          {"$int":"y2","value":"218"},
          {"$int":"prev","value":"26"},
          {"$int":"next","value":"29"},
          {"$int":"forbidFallDown","value":"1"}
        ]},
        {"$imgdir":"26","$$":[
          {"$int":"x1","value":"-250"},
          {"$int":"y1","value":"218"},
          {"$int":"x2","value":"75"},
          {"$int":"y2","value":"218"},
          {"$int":"prev","value":"9"},
          {"$int":"next","value":"25"},
          {"$int":"forbidFallDown","value":"1"}
        ]},
        {"$imgdir":"27","$$":[
          {"$int":"x1","value":"334"},
          {"$int":"y1","value":"200"},
          {"$int":"x2","value":"464"},
          {"$int":"y2","value":"200"},
          {"$int":"prev","value":"0"},
          {"$int":"next","value":"0"}
        ]},
        {"$imgdir":"28","$$":[
          {"$int":"x1","value":"353"},
          {"$int":"y1","value":"182"},
          {"$int":"x2","value":"472"},
          {"$int":"y2","value":"182"},
          {"$int":"prev","value":"0"},
          {"$int":"next","value":"0"}
        ]},
        {"$imgdir":"29","$$":[
          {"$int":"x1","value":"432"},
          {"$int":"y1","value":"218"},
          {"$int":"x2","value":"495"},
          {"$int":"y2","value":"218"},
          {"$int":"prev","value":"25"},
          {"$int":"next","value":"24"},
          {"$int":"forbidFallDown","value":"1"}
        ]}
      ]}
    ]}
  ]},
  {"$imgdir":"ladderRope"},
  {"$imgdir":"portal","$$":[
    {"$imgdir":"0","$$":[
      {"$string":"pn","value":"sp"},
      {"$int":"pt","value":"0"},
      {"$int":"x","value":"-122"},
      {"$int":"y","value":"166"},
      {"$int":"tm","value":"999999999"},
      {"$string":"tn","value":""}
    ]}
  ]}
]}