{"$imgdir":"925010400.img","$$":[
  {"$imgdir":"info","$$":[
    {"$int":"version","value":"10"},
    {"$int":"cloud","value":"0"},
    {"$int":"town","value":"0"},
    {"$int":"swim","value":"0"},
    {"$int":"returnMap","value":"925010400"},
    {"$int":"forcedReturn","value":"925010400"},
    {"$float":"mobRate","value":"1.0"},
    {"$string":"bgm","value":"Bgm15/inNautilus"},
    {"$string":"mapMark","value":"Quest"},
    {"$int":"hideMinimap","value":"0"},
    {"$int":"fieldLimit","value":"252"}
  ]},
  {"$imgdir":"back","$$":[
    {"$imgdir":"0","$$":[
      {"$string":"bS","value":""},
      {"$int":"front","value":"0"},
      {"$int":"ani","value":"0"},
      {"$int":"no","value":"0"},
      {"$int":"f","value":"0"},
      {"$int":"x","value":"0"},
      {"$int":"y","value":"0"},
      {"$int":"rx","value":"0"},
      {"$int":"ry","value":"0"},
      {"$int":"type","value":"0"},
      {"$int":"cx","value":"0"},
      {"$int":"cy","value":"0"},
      {"$int":"a","value":"255"}
    ]}
  ]},
  {"$imgdir":"life","$$":[
    {"$imgdir":"0","$$":[
      {"$string":"type","value":"n"},
      {"$string":"id","value":"2095000"},
      {"$int":"x","value":"381"},
      {"$int":"y","value":"134"},
      {"$int":"mobTime","value":"0"},
      {"$int":"f","value":"0"},
      {"$int":"hide","value":"0"},
      {"$int":"fh","value":"6"},
      {"$int":"cy","value":"150"},
      {"$int":"rx0","value":"331"},
      {"$int":"rx1","value":"431"}
    ]}
  ]},
  {"$imgdir":"reactor"},
  {"$imgdir":"0","$$":[
    {"$imgdir":"info"},
    {"$imgdir":"tile"},
    {"$imgdir":"obj"}
  ]},
  {"$imgdir":"1","$$":[
    {"$imgdir":"info"},
    {"$imgdir":"tile"},
    {"$imgdir":"obj"}
  ]},
  {"$imgdir":"2","$$":[
    {"$imgdir":"info"},
    {"$imgdir":"tile"},
    {"$imgdir":"obj"}
  ]},
  {"$imgdir":"3","$$":[
    {"$imgdir":"info"},
    {"$imgdir":"tile"},
    {"$imgdir":"obj","$$":[
      {"$imgdir":"0","$$":[
        {"$string":"oS","value":"acc9"},
        {"$string":"l0","value":"inside"},
        {"$string":"l1","value":"back"},
        {"$string":"l2","value":"0"},
        {"$int":"x","value":"-251"},
        {"$int":"y","value":"-76"},
        {"$int":"z","value":"9"},
        {"$int":"f","value":"0"},
        {"$int":"zM","value":"2"},
        {"$int":"r","value":"0"}
      ]},
      {"$imgdir":"1","$$":[
        {"$string":"oS","value":"acc9"},
        {"$string":"l0","value":"inside"},
        {"$string":"l1","value":"back"},
        {"$string":"l2","value":"1"},
        {"$int":"x","value":"49"},
        {"$int":"y","value":"-76"},
        {"$int":"z","value":"9"},
        {"$int":"f","value":"0"},
        {"$int":"zM","value":"3"},
        {"$int":"r","value":"0"}
      ]},
      {"$imgdir":"2","$$":[
        {"$string":"oS","value":"acc9"},
        {"$string":"l0","value":"inside"},
        {"$string":"l1","value":"back"},
        {"$string":"l2","value":"0"},
        {"$int":"x","value":"349"},
        {"$int":"y","value":"-75"},
        {"$int":"z","value":"9"},
        {"$int":"f","value":"0"},
        {"$int":"zM","value":"1"},
        {"$int":"r","value":"0"}
      ]}
    ]}
  ]},
  {"$imgdir":"4","$$":[
    {"$imgdir":"info"},
    {"$imgdir":"tile"},
    {"$imgdir":"obj"}
  ]},
  {"$imgdir":"5","$$":[
    {"$imgdir":"info"},
    {"$imgdir":"tile"},
    {"$imgdir":"obj","$$":[
      {"$imgdir":"0","$$":[
        {"$string":"oS","value":"acc9"},
        {"$string":"l0","value":"inside"},
        {"$string":"l1","value":"etc"},
        {"$string":"l2","value":"0"},
        {"$int":"x","value":"-326"},
        {"$int":"y","value":"224"},
        {"$int":"z","value":"9"},
        {"$int":"f","value":"0"},
        {"$int":"zM","value":"0"},
        {"$int":"r","value":"0"}
      ]},
      {"$imgdir":"1","$$":[
        {"$string":"oS","value":"acc9"},
        {"$string":"l0","value":"inside"},
        {"$string":"l1","value":"etc"},
        {"$string":"l2","value":"0"},
        {"$int":"x","value":"-177"},
        {"$int":"y","value":"224"},
        {"$int":"z","value":"9"},
        {"$int":"f","value":"0"},
        {"$int":"zM","value":"0"},
        {"$int":"r","value":"0"}
      ]},
      {"$imgdir":"2","$$":[
        {"$string":"oS","value":"acc9"},
        {"$string":"l0","value":"inside"},
        {"$string":"l1","value":"etc"},
        {"$string":"l2","value":"0"},
        {"$int":"x","value":"-28"},
        {"$int":"y","value":"224"},
        {"$int":"z","value":"9"},
        {"$int":"f","value":"0"},
        {"$int":"zM","value":"0"},
        {"$int":"r","value":"0"}
      ]},
      {"$imgdir":"3","$$":[
        {"$string":"oS","value":"acc9"},
        {"$string":"l0","value":"inside"},
        {"$string":"l1","value":"etc"},
        {"$string":"l2","value":"0"},
        {"$int":"x","value":"121"},
        {"$int":"y","value":"224"},
        {"$int":"z","value":"9"},
        {"$int":"f","value":"0"},
        {"$int":"zM","value":"0"},
        {"$int":"r","value":"0"}
      ]},
      {"$imgdir":"4","$$":[
        {"$string":"oS","value":"acc9"},
        {"$string":"l0","value":"inside"},
        {"$string":"l1","value":"etc"},
        {"$string":"l2","value":"0"},
        {"$int":"x","value":"270"},
        {"$int":"y","value":"224"},
        {"$int":"z","value":"9"},
        {"$int":"f","value":"0"},
        {"$int":"zM","value":"0"},
        {"$int":"r","value":"0"}
      ]},
      {"$imgdir":"5","$$":[
        {"$string":"oS","value":"acc9"},
        {"$string":"l0","value":"inside"},
        {"$string":"l1","value":"etc"},
        {"$string":"l2","value":"0"},
        {"$int":"x","value":"419"},
        {"$int":"y","value":"224"},
        {"$int":"z","value":"9"},
        {"$int":"f","value":"0"},
        {"$int":"zM","value":"0"},
        {"$int":"r","value":"0"}
      ]},
      {"$imgdir":"6","$$":[
        {"$string":"oS","value":"acc9"},
        {"$string":"l0","value":"inside"},
        {"$string":"l1","value":"etc"},
        {"$string":"l2","value":"0"},
        {"$int":"x","value":"424"},
        {"$int":"y","value":"224"},
        {"$int":"z","value":"9"},
        {"$int":"f","value":"0"},
        {"$int":"zM","value":"0"},
        {"$int":"r","value":"0"}
      ]}
    ]}
  ]},
  {"$imgdir":"6","$$":[
    {"$imgdir":"info"},
    {"$imgdir":"tile"},
    {"$imgdir":"obj"}
  ]},
  {"$imgdir":"7","$$":[
    {"$imgdir":"info"},
    {"$imgdir":"tile"},
    {"$imgdir":"obj"}
  ]},
  {"$imgdir":"foothold","$$":[
    {"$imgdir":"5","$$":[
      {"$imgdir":"0","$$":[
        {"$imgdir":"1","$$":[
          {"$int":"x1","value":"-402"},
          {"$int":"y1","value":"150"},
          {"$int":"x2","value":"-249"},
          {"$int":"y2","value":"150"},
          {"$int":"prev","value":"0"},
          {"$int":"next","value":"2"}
        ]},
        {"$imgdir":"2","$$":[
          {"$int":"x1","value":"-249"},
          {"$int":"y1","value":"150"},
          {"$int":"x2","value":"-100"},
          {"$int":"y2","value":"150"},
          {"$int":"prev","value":"1"},
          {"$int":"next","value":"3"}
        ]},
        {"$imgdir":"3","$$":[
          {"$int":"x1","value":"-100"},
          {"$int":"y1","value":"150"},
          {"$int":"x2","value":"49"},
          {"$int":"y2","value":"150"},
          {"$int":"prev","value":"2"},
          {"$int":"next","value":"4"}
        ]},
        {"$imgdir":"4","$$":[
          {"$int":"x1","value":"49"},
          {"$int":"y1","value":"150"},
          {"$int":"x2","value":"198"},
          {"$int":"y2","value":"150"},
          {"$int":"prev","value":"3"},
          {"$int":"next","value":"5"}
        ]},
        {"$imgdir":"5","$$":[
          {"$int":"x1","value":"198"},
          {"$int":"y1","value":"150"},
          {"$int":"x2","value":"347"},
          {"$int":"y2","value":"150"},
          {"$int":"prev","value":"4"},
          {"$int":"next","value":"6"}
        ]},
        {"$imgdir":"6","$$":[
          {"$int":"x1","value":"347"},
          {"$int":"y1","value":"150"},
          {"$int":"x2","value":"496"},
          {"$int":"y2","value":"150"},
          {"$int":"prev","value":"5"},
          {"$int":"next","value":"7"}
        ]},
        {"$imgdir":"7","$$":[
          {"$int":"x1","value":"496"},
          {"$int":"y1","value":"150"},
          {"$int":"x2","value":"501"},
          {"$int":"y2","value":"150"},
          {"$int":"prev","value":"6"},
          {"$int":"next","value":"0"}
        ]}
      ]}
    ]}
  ]},
  {"$imgdir":"ladderRope"},
  {"$imgdir":"portal","$$":[
    {"$imgdir":"0","$$":[
      {"$string":"pn","value":"sp"},
      {"$int":"pt","value":"0"},
      {"$int":"x","value":"8"},
      {"$int":"y","value":"66"},
      {"$int":"tm","value":"999999999"},
      {"$string":"tn","value":""}
    ]}
  ]}
]}