{"$imgdir":"925100700.img","$$":[
  {"$imgdir":"info","$$":[
    {"$int":"version","value":"10"},
    {"$int":"cloud","value":"0"},
    {"$int":"town","value":"0"},
    {"$int":"swim","value":"0"},
    {"$int":"returnMap","value":"925100700"},
    {"$int":"forcedReturn","value":"925100700"},
    {"$float":"mobRate","value":"1.0"},
    {"$string":"bgm","value":"Bgm15/Pirate"},
    {"$string":"mapMark","value":"DevijonParty"},
    {"$int":"hideMinimap","value":"0"},
    {"$int":"fieldLimit","value":"271096"},
    {"$int":"VRTop","value":"-545"},
    {"$int":"VRLeft","value":"-126"},
    {"$int":"VRBottom","value":"438"},
    {"$int":"VRRight","value":"927"}
  ]},
  {"$imgdir":"back","$$":[
    {"$imgdir":"0","$$":[
      {"$string":"bS","value":"backcho"},
      {"$int":"front","value":"0"},
      {"$int":"ani","value":"0"},
      {"$int":"no","value":"0"},
      {"$int":"f","value":"0"},
      {"$int":"x","value":"0"},
      {"$int":"y","value":"0"},
      {"$int":"rx","value":"0"},
      {"$int":"ry","value":"0"},
      {"$int":"type","value":"3"},
      {"$int":"cx","value":"0"},
      {"$int":"cy","value":"0"},
      {"$int":"a","value":"255"}
    ]},
    {"$imgdir":"1","$$":[
      {"$string":"bS","value":"backcho"},
      {"$int":"front","value":"0"},
      {"$int":"ani","value":"0"},
      {"$int":"no","value":"1"},
      {"$int":"f","value":"0"},
      {"$int":"x","value":"84"},
      {"$int":"y","value":"-30"},
      {"$int":"rx","value":"-5"},
      {"$int":"ry","value":"-5"},
      {"$int":"type","value":"1"},
      {"$int":"cx","value":"0"},
      {"$int":"cy","value":"0"},
      {"$int":"a","value":"255"}
    ]},
    {"$imgdir":"2","$$":[
      {"$string":"bS","value":"backcho"},
      {"$int":"front","value":"0"},
      {"$int":"ani","value":"0"},
      {"$int":"no","value":"21"},
      {"$int":"f","value":"0"},
      {"$int":"x","value":"-29"},
      {"$int":"y","value":"8"},
      {"$int":"rx","value":"-2"},
      {"$int":"ry","value":"-5"},
      {"$int":"type","value":"4"},
      {"$int":"cx","value":"0"},
      {"$int":"cy","value":"0"},
      {"$int":"a","value":"255"}
    ]},
    {"$imgdir":"3","$$":[
      {"$string":"bS","value":"backcho"},
      {"$int":"front","value":"0"},
      {"$int":"ani","value":"0"},
      {"$int":"no","value":"22"},
      {"$int":"f","value":"0"},
      {"$int":"x","value":"-10"},
      {"$int":"y","value":"46"},
      {"$int":"rx","value":"-3"},
      {"$int":"ry","value":"-18"},
      {"$int":"type","value":"4"},
      {"$int":"cx","value":"0"},
      {"$int":"cy","value":"0"},
      {"$int":"a","value":"255"}
    ]},
    {"$imgdir":"4","$$":[
      {"$string":"bS","value":"backcho"},
      {"$int":"front","value":"0"},
      {"$int":"ani","value":"0"},
      {"$int":"no","value":"23"},
      {"$int":"f","value":"0"},
      {"$int":"x","value":"-448"},
      {"$int":"y","value":"12"},
      {"$int":"rx","value":"-5"},
      {"$int":"ry","value":"-40"},
      {"$int":"type","value":"4"},
      {"$int":"cx","value":"1600"},
      {"$int":"cy","value":"0"},
      {"$int":"a","value":"255"}
    ]},
    {"$imgdir":"5","$$":[
      {"$string":"bS","value":"backcho"},
      {"$int":"front","value":"0"},
      {"$int":"ani","value":"0"},
      {"$int":"no","value":"24"},
      {"$int":"f","value":"0"},
      {"$int":"x","value":"352"},
      {"$int":"y","value":"32"},
      {"$int":"rx","value":"-5"},
      {"$int":"ry","value":"-40"},
      {"$int":"type","value":"4"},
      {"$int":"cx","value":"1600"},
      {"$int":"cy","value":"0"},
      {"$int":"a","value":"255"}
    ]},
    {"$imgdir":"8","$$":[
      {"$string":"bS","value":"backcho"},
      {"$int":"front","value":"0"},
      {"$int":"ani","value":"0"},
      {"$int":"no","value":"11"},
      {"$int":"f","value":"0"},
      {"$int":"x","value":"257"},
      {"$int":"y","value":"67"},
      {"$int":"rx","value":"-4"},
      {"$int":"ry","value":"-40"},
      {"$int":"type","value":"4"},
      {"$int":"cx","value":"900"},
      {"$int":"cy","value":"0"},
      {"$int":"a","value":"255"}
    ]},
    {"$imgdir":"10","$$":[
      {"$string":"bS","value":"backcho"},
      {"$int":"front","value":"0"},
      {"$int":"ani","value":"0"},
      {"$int":"no","value":"13"},
      {"$int":"f","value":"0"},
      {"$int":"x","value":"11"},
      {"$int":"y","value":"92"},
      {"$int":"rx","value":"-8"},
      {"$int":"ry","value":"-90"},
      {"$int":"type","value":"4"},
      {"$int":"cx","value":"1500"},
      {"$int":"cy","value":"0"},
      {"$int":"a","value":"255"}
    ]},
    {"$imgdir":"11","$$":[
      {"$string":"bS","value":"backcho"},
      {"$int":"front","value":"0"},
      {"$int":"ani","value":"0"},
      {"$int":"no","value":"14"},
      {"$int":"f","value":"0"},
      {"$int":"x","value":"311"},
      {"$int":"y","value":"136"},
      {"$int":"rx","value":"-8"},
      {"$int":"ry","value":"-90"},
      {"$int":"type","value":"4"},
      {"$int":"cx","value":"1500"},
      {"$int":"cy","value":"0"},
      {"$int":"a","value":"255"}
    ]},
    {"$imgdir":"12","$$":[
      {"$string":"bS","value":"backcho"},
      {"$int":"front","value":"0"},
      {"$int":"ani","value":"0"},
      {"$int":"no","value":"15"},
      {"$int":"f","value":"0"},
      {"$int":"x","value":"611"},
      {"$int":"y","value":"131"},
      {"$int":"rx","value":"-8"},
      {"$int":"ry","value":"-90"},
      {"$int":"type","value":"4"},
      {"$int":"cx","value":"1500"},
      {"$int":"cy","value":"0"},
      {"$int":"a","value":"255"}
    ]},
    {"$imgdir":"6","$$":[
      {"$string":"bS","value":"backcho"},
      {"$int":"front","value":"0"},
      {"$int":"ani","value":"0"},
      {"$int":"no","value":"12"},
      {"$int":"f","value":"0"},
      {"$int":"x","value":"302"},
      {"$int":"y","value":"44"},
      {"$int":"rx","value":"-3"},
      {"$int":"ry","value":"-40"},
      {"$int":"type","value":"4"},
      {"$int":"cx","value":"1100"},
      {"$int":"cy","value":"0"},
      {"$int":"a","value":"255"}
    ]},
    {"$imgdir":"13","$$":[
      {"$string":"bS","value":"backcho"},
      {"$int":"front","value":"0"},
      {"$int":"ani","value":"0"},
      {"$int":"no","value":"16"},
      {"$int":"f","value":"0"},
      {"$int":"x","value":"911"},
      {"$int":"y","value":"151"},
      {"$int":"rx","value":"-8"},
      {"$int":"ry","value":"-90"},
      {"$int":"type","value":"4"},
      {"$int":"cx","value":"1500"},
      {"$int":"cy","value":"0"},
      {"$int":"a","value":"255"}
    ]},
    {"$imgdir":"14","$$":[
      {"$string":"bS","value":"backcho"},
      {"$int":"front","value":"0"},
      {"$int":"ani","value":"0"},
      {"$int":"no","value":"17"},
      {"$int":"f","value":"0"},
      {"$int":"x","value":"-289"},
      {"$int":"y","value":"102"},
      {"$int":"rx","value":"-8"},
      {"$int":"ry","value":"-90"},
      {"$int":"type","value":"4"},
      {"$int":"cx","value":"1500"},
      {"$int":"cy","value":"0"},
      {"$int":"a","value":"255"}
    ]},
    {"$imgdir":"15","$$":[
      {"$string":"bS","value":"backcho"},
      {"$int":"front","value":"1"},
      {"$int":"ani","value":"0"},
      {"$int":"no","value":"18"},
      {"$int":"f","value":"0"},
      {"$int":"x","value":"18"},
      {"$int":"y","value":"353"},
      {"$int":"rx","value":"-10"},
      {"$int":"ry","value":"-100"},
      {"$int":"type","value":"4"},
      {"$int":"cx","value":"0"},
      {"$int":"cy","value":"0"},
      {"$int":"a","value":"255"}
    ]},
    {"$imgdir":"9","$$":[
      {"$string":"bS","value":"backcho"},
      {"$int":"front","value":"0"},
      {"$int":"ani","value":"0"},
      {"$int":"no","value":"10"},
      {"$int":"f","value":"0"},
      {"$int":"x","value":"248"},
      {"$int":"y","value":"26"},
      {"$int":"rx","value":"-4"},
      {"$int":"ry","value":"-40"},
      {"$int":"type","value":"4"},
      {"$int":"cx","value":"1000"},
      {"$int":"cy","value":"0"},
      {"$int":"a","value":"255"}
    ]},
    {"$imgdir":"7","$$":[
      {"$string":"bS","value":"backcho"},
      {"$int":"front","value":"0"},
      {"$int":"ani","value":"0"},
      {"$int":"no","value":"9"},
      {"$int":"f","value":"0"},
      {"$int":"x","value":"1"},
      {"$int":"y","value":"72"},
      {"$int":"rx","value":"-5"},
      {"$int":"ry","value":"-40"},
      {"$int":"type","value":"4"},
      {"$int":"cx","value":"1300"},
      {"$int":"cy","value":"0"},
      {"$int":"a","value":"255"}
    ]},
    {"$imgdir":"16","$$":[
      {"$string":"bS","value":"backcho"},
      {"$int":"front","value":"1"},
      {"$int":"ani","value":"0"},
      {"$int":"no","value":"19"},
      {"$int":"f","value":"0"},
      {"$int":"x","value":"20"},
      {"$int":"y","value":"359"},
      {"$int":"rx","value":"-13"},
      {"$int":"ry","value":"-100"},
      {"$int":"type","value":"4"},
      {"$int":"cx","value":"0"},
      {"$int":"cy","value":"0"},
      {"$int":"a","value":"255"}
    ]}
  ]},
  {"$imgdir":"life","$$":[
    {"$imgdir":"0","$$":[
      {"$string":"type","value":"n"},
      {"$string":"id","value":"2094002"},
      {"$int":"x","value":"647"},
      {"$int":"y","value":"94"},
      {"$int":"mobTime","value":"0"},
      {"$int":"f","value":"0"},
      {"$int":"hide","value":"0"},
      {"$int":"fh","value":"1"},
      {"$int":"cy","value":"100"},
      {"$int":"rx0","value":"597"},
      {"$int":"rx1","value":"697"}
    ]}
  ]},
  {"$imgdir":"reactor"},
  {"$imgdir":"0","$$":[
    {"$imgdir":"info"},
    {"$imgdir":"tile"},
    {"$imgdir":"obj"}
  ]},
  {"$imgdir":"1","$$":[
    {"$imgdir":"info"},
    {"$imgdir":"tile"},
    {"$imgdir":"obj"}
  ]},
  {"$imgdir":"2","$$":[
    {"$imgdir":"info"},
    {"$imgdir":"tile"},
    {"$imgdir":"obj","$$":[
      {"$imgdir":"1","$$":[
        {"$string":"oS","value":"acc7"},
        {"$string":"l0","value":"backchoField"},
        {"$string":"l1","value":"nature"},
        {"$string":"l2","value":"2"},
        {"$int":"x","value":"821"},
        {"$int":"y","value":"99"},
        {"$int":"z","value":"0"},
        {"$int":"f","value":"0"},
        {"$int":"zM","value":"2"},
        {"$string":"rx","value":"-11"},
        {"$int":"flow","value":"1"},
        {"$string":"ry","value":"2000"}
      ]},
      {"$imgdir":"2","$$":[
        {"$string":"oS","value":"acc7"},
        {"$string":"l0","value":"backchoField"},
        {"$string":"l1","value":"nature"},
        {"$string":"l2","value":"3"},
        {"$int":"x","value":"356"},
        {"$int":"y","value":"202"},
        {"$int":"z","value":"0"},
        {"$int":"f","value":"0"},
        {"$int":"zM","value":"2"},
        {"$int":"flow","value":"1"},
        {"$string":"rx","value":"-11"},
        {"$string":"ry","value":"2000"}
      ]},
      {"$imgdir":"0","$$":[
        {"$string":"oS","value":"acc7"},
        {"$string":"l0","value":"backchoField"},
        {"$string":"l1","value":"ship"},
        {"$string":"l2","value":"20"},
        {"$int":"x","value":"632"},
        {"$int":"y","value":"169"},
        {"$int":"z","value":"9"},
        {"$int":"f","value":"0"},
        {"$int":"zM","value":"2"}
      ]},
      {"$imgdir":"4","$$":[
        {"$string":"oS","value":"acc7"},
        {"$string":"l0","value":"backchoField"},
        {"$string":"l1","value":"acc"},
        {"$string":"l2","value":"3"},
        {"$int":"x","value":"160"},
        {"$int":"y","value":"126"},
        {"$int":"z","value":"4"},
        {"$int":"f","value":"0"},
        {"$int":"zM","value":"0"}
      ]},
      {"$imgdir":"3","$$":[
        {"$string":"oS","value":"acc7"},
        {"$string":"l0","value":"backchoField"},
        {"$string":"l1","value":"acc"},
        {"$string":"l2","value":"2"},
        {"$int":"x","value":"148"},
        {"$int":"y","value":"132"},
        {"$int":"z","value":"9"},
        {"$int":"f","value":"0"},
        {"$int":"zM","value":"0"}
      ]}
    ]}
  ]},
  {"$imgdir":"3","$$":[
    {"$imgdir":"info"},
    {"$imgdir":"tile"},
    {"$imgdir":"obj","$$":[
      {"$imgdir":"1","$$":[
        {"$string":"oS","value":"acc7"},
        {"$string":"l0","value":"backchoField"},
        {"$string":"l1","value":"ship"},
        {"$string":"l2","value":"2"},
        {"$int":"x","value":"72"},
        {"$int":"y","value":"319"},
        {"$int":"z","value":"10"},
        {"$int":"f","value":"0"},
        {"$int":"zM","value":"0"}
      ]},
      {"$imgdir":"0","$$":[
        {"$string":"oS","value":"acc7"},
        {"$string":"l0","value":"backchoField"},
        {"$string":"l1","value":"ship"},
        {"$string":"l2","value":"3"},
        {"$int":"x","value":"426"},
        {"$int":"y","value":"319"},
        {"$int":"z","value":"10"},
        {"$int":"f","value":"0"},
        {"$int":"zM","value":"0"}
      ]},
      {"$imgdir":"2","$$":[
        {"$string":"oS","value":"acc7"},
        {"$string":"l0","value":"backchoField"},
        {"$string":"l1","value":"ship"},
        {"$string":"l2","value":"2"},
        {"$int":"x","value":"729"},
        {"$int":"y","value":"319"},
        {"$int":"z","value":"7"},
        {"$int":"f","value":"0"},
        {"$int":"zM","value":"0"}
      ]}
    ]}
  ]},
  {"$imgdir":"4","$$":[
    {"$imgdir":"info"},
    {"$imgdir":"tile"},
    {"$imgdir":"obj"}
  ]},
  {"$imgdir":"5","$$":[
    {"$imgdir":"info"},
    {"$imgdir":"tile"},
    {"$imgdir":"obj"}
  ]},
  {"$imgdir":"6","$$":[
    {"$imgdir":"info"},
    {"$imgdir":"tile"},
    {"$imgdir":"obj"}
  ]},
  {"$imgdir":"7","$$":[
    {"$imgdir":"info"},
    {"$imgdir":"tile"},
    {"$imgdir":"obj"}
  ]},
  {"$imgdir":"foothold","$$":[
    {"$imgdir":"2","$$":[
      {"$imgdir":"2","$$":[
        {"$imgdir":"1","$$":[
          {"$int":"x1","value":"478"},
          {"$int":"y1","value":"100"},
          {"$int":"x2","value":"795"},
          {"$int":"y2","value":"100"},
          {"$int":"prev","value":"0"},
          {"$int":"next","value":"0"}
        ]},
        {"$imgdir":"2","$$":[
          {"$int":"x1","value":"487"},
          {"$int":"y1","value":"133"},
          {"$int":"x2","value":"559"},
          {"$int":"y2","value":"133"},
          {"$int":"prev","value":"0"},
          {"$int":"next","value":"3"}
        ]},
        {"$imgdir":"3","$$":[
          {"$int":"x1","value":"559"},
          {"$int":"y1","value":"133"},
          {"$int":"x2","value":"586"},
          {"$int":"y2","value":"137"},
          {"$int":"prev","value":"2"},
          {"$int":"next","value":"0"}
        ]},
        {"$imgdir":"4","$$":[
          {"$int":"x1","value":"467"},
          {"$int":"y1","value":"168"},
          {"$int":"x2","value":"564"},
          {"$int":"y2","value":"168"},
          {"$int":"prev","value":"0"},
          {"$int":"next","value":"0"}
        ]},
        {"$imgdir":"5","$$":[
          {"$int":"x1","value":"447"},
          {"$int":"y1","value":"204"},
          {"$int":"x2","value":"541"},
          {"$int":"y2","value":"204"},
          {"$int":"prev","value":"0"},
          {"$int":"next","value":"0"}
        ]}
      ]}
    ]},
    {"$imgdir":"3","$$":[
      {"$imgdir":"0","$$":[
        {"$imgdir":"6","$$":[
          {"$int":"x1","value":"221"},
          {"$int":"y1","value":"238"},
          {"$int":"x2","value":"632"},
          {"$int":"y2","value":"238"},
          {"$int":"prev","value":"7"},
          {"$int":"next","value":"8"}
        ]},
        {"$imgdir":"7","$$":[
          {"$int":"x1","value":"-133"},
          {"$int":"y1","value":"238"},
          {"$int":"x2","value":"221"},
          {"$int":"y2","value":"238"},
          {"$int":"prev","value":"0"},
          {"$int":"next","value":"6"}
        ]},
        {"$imgdir":"8","$$":[
          {"$int":"x1","value":"632"},
          {"$int":"y1","value":"238"},
          {"$int":"x2","value":"935"},
          {"$int":"y2","value":"238"},
          {"$int":"prev","value":"6"},
          {"$int":"next","value":"0"}
        ]}
      ]}
    ]}
  ]},
  {"$imgdir":"ladderRope"},
  {"$imgdir":"portal","$$":[
    {"$imgdir":"0","$$":[
      {"$string":"pn","value":"sp"},
      {"$int":"pt","value":"0"},
      {"$int":"x","value":"83"},
      {"$int":"y","value":"160"},
      {"$int":"tm","value":"999999999"},
      {"$string":"tn","value":""}
    ]}
  ]}
]}